{"shard":"喆","count":243,"data":{"喆泰科技股份有限公司":{"name":"喆泰科技股份有限公司","id":"132322","capital":100000,"representative":"張_真","address":"臺北市大同區南京西路163號2樓之54","aliases":[],"relationships":{"upstream":[],"downstream":[]},"webUrl":"https://tbdavid2019.github.io/taiwan-company-network/graph?company=%E5%96%86%E6%B3%B0%E7%A7%91%E6%8A%80%E8%82%A1%E4%BB%BD%E6%9C%89%E9%99%90%E5%85%AC%E5%8F%B8"},"喆林室內裝修工程有限公司":{"name":"喆林室內裝修工程有限公司","id":"135756","capital":1000000,"representative":"莊_有","address":"桃園市桃園區北埔里中正路1415號(2樓)","aliases":[],"relationships":{"upstream":[],"downstream":[]},"webUrl":"https://tbdavid2019.github.io/taiwan-company-network/graph?company=%E5%96%86%E6%9E%97%E5%AE%A4%E5%85%A7%E8%A3%9D%E4%BF%AE%E5%B7%A5%E7%A8%8B%E6%9C%89%E9%99%90%E5%85%AC%E5%8F%B8"},"喆遇設計有限公司":{"name":"喆遇設計有限公司","id":"204084","capital":1000000,"representative":"李_華","address":"臺北市信義區忠孝東路5段1之8號12樓","aliases":[],"relationships":{"upstream":[],"downstream":[]},"webUrl":"https://tbdavid2019.github.io/taiwan-company-network/graph?company=%E5%96%86%E9%81%87%E8%A8%AD%E8%A8%88%E6%9C%89%E9%99%90%E5%85%AC%E5%8F%B8"},"喆甡企業有限公司":{"name":"喆甡企業有限公司","id":"4747439","capital":2000000,"representative":"金_玨","address":"臺北市大同區長安西路78巷4弄3號4樓","aliases":[],"relationships":{"upstream":[],"downstream":[]},"webUrl":"https://tbdavid2019.github.io/taiwan-company-network/graph?company=%E5%96%86%E7%94%A1%E4%BC%81%E6%A5%AD%E6%9C%89%E9%99%90%E5%85%AC%E5%8F%B8"},"喆羊有限公司":{"name":"喆羊有限公司","id":"12383002","capital":1000000,"representative":"陳_平","address":"臺北市中山區南京東路3段14巷42號2樓","aliases":[],"relationships":{"upstream":[],"downstream":[]},"webUrl":"https://tbdavid2019.github.io/taiwan-company-network/graph?company=%E5%96%86%E7%BE%8A%E6%9C%89%E9%99%90%E5%85%AC%E5%8F%B8"},"喆明實業有限公司":{"name":"喆明實業有限公司","id":"12886074","capital":1000000,"representative":"許_蓮","address":"新北市八里區中華路2段552號13樓  ","aliases":[],"relationships":{"upstream":[],"downstream":[]},"webUrl":"https://tbdavid2019.github.io/taiwan-company-network/graph?company=%E5%96%86%E6%98%8E%E5%AF%A6%E6%A5%AD%E6%9C%89%E9%99%90%E5%85%AC%E5%8F%B8"},"喆盤古形象設計有限公司":{"name":"喆盤古形象設計有限公司","id":"16239459","capital":2000000,"representative":"顏_杰","address":"臺中市西屯區長安路一段41之5號1樓","aliases":[],"relationships":{"upstream":[],"downstream":[]},"webUrl":"https://tbdavid2019.github.io/taiwan-company-network/graph?company=%E5%96%86%E7%9B%A4%E5%8F%A4%E5%BD%A2%E8%B1%A1%E8%A8%AD%E8%A8%88%E6%9C%89%E9%99%90%E5%85%AC%E5%8F%B8"},"喆祿實業股份有限公司":{"name":"喆祿實業股份有限公司","id":"20892492","capital":5000000,"representative":"吳_順","address":"臺北市中山區八德路2段447號3樓","aliases":[],"relationships":{"upstream":[],"downstream":[]},"webUrl":"https://tbdavid2019.github.io/taiwan-company-network/graph?company=%E5%96%86%E7%A5%BF%E5%AF%A6%E6%A5%AD%E8%82%A1%E4%BB%BD%E6%9C%89%E9%99%90%E5%85%AC%E5%8F%B8"},"喆昌貿易有限公司":{"name":"喆昌貿易有限公司","id":"20911651","capital":5000000,"representative":"陳_貞","address":"臺北市松山區民生東路5段93號2樓","aliases":[],"relationships":{"upstream":[],"downstream":[]},"webUrl":"https://tbdavid2019.github.io/taiwan-company-network/graph?company=%E5%96%86%E6%98%8C%E8%B2%BF%E6%98%93%E6%9C%89%E9%99%90%E5%85%AC%E5%8F%B8"},"喆弘企業有限公司":{"name":"喆弘企業有限公司","id":"22089680","capital":1000000,"representative":"李_樑","address":"臺中市太平區德隆里工業16路2號","aliases":[],"relationships":{"upstream":[],"downstream":[]},"webUrl":"https://tbdavid2019.github.io/taiwan-company-network/graph?company=%E5%96%86%E5%BC%98%E4%BC%81%E6%A5%AD%E6%9C%89%E9%99%90%E5%85%AC%E5%8F%B8"},"喆門電子有限公司":{"name":"喆門電子有限公司","id":"22118502","capital":1000000,"representative":"劉_旗","address":"基隆市中正區砂子里調和街290巷199號  ","aliases":[],"relationships":{"upstream":[],"downstream":[]},"webUrl":"https://tbdavid2019.github.io/taiwan-company-network/graph?company=%E5%96%86%E9%96%80%E9%9B%BB%E5%AD%90%E6%9C%89%E9%99%90%E5%85%AC%E5%8F%B8"},"喆成企業有限公司":{"name":"喆成企業有限公司","id":"23178507","capital":5000000,"representative":"張_琳","address":"臺中市豐原區西湳里三豐路二段57巷20弄11號  ","aliases":[],"relationships":{"upstream":[],"downstream":[]},"webUrl":"https://tbdavid2019.github.io/taiwan-company-network/graph?company=%E5%96%86%E6%88%90%E4%BC%81%E6%A5%AD%E6%9C%89%E9%99%90%E5%85%AC%E5%8F%B8"},"喆泰企業股份有限公司":{"name":"喆泰企業股份有限公司","id":"23560460","capital":30000000,"representative":"張_鶯","address":"雲林縣斗六市榴中里工業路101號","aliases":[],"relationships":{"upstream":[],"downstream":[]},"webUrl":"https://tbdavid2019.github.io/taiwan-company-network/graph?company=%E5%96%86%E6%B3%B0%E4%BC%81%E6%A5%AD%E8%82%A1%E4%BB%BD%E6%9C%89%E9%99%90%E5%85%AC%E5%8F%B8"},"喆臨貿易有限公司":{"name":"喆臨貿易有限公司","id":"23660897","capital":5000000,"representative":"黃_臨","address":"高雄市三民區九如一路502號19樓之1","aliases":[],"relationships":{"upstream":[],"downstream":[]},"webUrl":"https://tbdavid2019.github.io/taiwan-company-network/graph?company=%E5%96%86%E8%87%A8%E8%B2%BF%E6%98%93%E6%9C%89%E9%99%90%E5%85%AC%E5%8F%B8"},"喆大企業有限公司":{"name":"喆大企業有限公司","id":"23749680","capital":1000000,"representative":"莊_仙","address":"臺北市中山區復興北路514巷47號1樓","aliases":[],"relationships":{"upstream":[],"downstream":[]},"webUrl":"https://tbdavid2019.github.io/taiwan-company-network/graph?company=%E5%96%86%E5%A4%A7%E4%BC%81%E6%A5%AD%E6%9C%89%E9%99%90%E5%85%AC%E5%8F%B8"},"喆暉企業有限公司":{"name":"喆暉企業有限公司","id":"23951213","capital":15000000,"representative":"葉_民","address":"雲林縣莿桐鄉興貴村興北20-1號","aliases":[],"relationships":{"upstream":[],"downstream":[]},"webUrl":"https://tbdavid2019.github.io/taiwan-company-network/graph?company=%E5%96%86%E6%9A%89%E4%BC%81%E6%A5%AD%E6%9C%89%E9%99%90%E5%85%AC%E5%8F%B8"},"喆品食品有限公司":{"name":"喆品食品有限公司","id":"24324015","capital":300000,"representative":"江_盈","address":"臺北市北投區東華街2段220號1樓","aliases":[],"relationships":{"upstream":[],"downstream":[]},"webUrl":"https://tbdavid2019.github.io/taiwan-company-network/graph?company=%E5%96%86%E5%93%81%E9%A3%9F%E5%93%81%E6%9C%89%E9%99%90%E5%85%AC%E5%8F%B8"},"喆慶企業有限公司":{"name":"喆慶企業有限公司","id":"24513445","capital":1000000,"representative":"林_真","address":"高雄市三民區德山街34號10樓","aliases":[],"relationships":{"upstream":[],"downstream":[]},"webUrl":"https://tbdavid2019.github.io/taiwan-company-network/graph?company=%E5%96%86%E6%85%B6%E4%BC%81%E6%A5%AD%E6%9C%89%E9%99%90%E5%85%AC%E5%8F%B8"},"喆麗生技有限公司":{"name":"喆麗生技有限公司","id":"24622680","capital":1000000,"representative":"李_傑","address":"嘉義縣義竹鄉傳芳村義竹506之2號","aliases":[],"relationships":{"upstream":[],"downstream":[]},"webUrl":"https://tbdavid2019.github.io/taiwan-company-network/graph?company=%E5%96%86%E9%BA%97%E7%94%9F%E6%8A%80%E6%9C%89%E9%99%90%E5%85%AC%E5%8F%B8"},"喆發汽車有限公司":{"name":"喆發汽車有限公司","id":"24627995","capital":10000000,"representative":"余_儒","address":"宜蘭縣宜蘭市小東里新興路9號","aliases":[],"relationships":{"upstream":[],"downstream":[]},"webUrl":"https://tbdavid2019.github.io/taiwan-company-network/graph?company=%E5%96%86%E7%99%BC%E6%B1%BD%E8%BB%8A%E6%9C%89%E9%99%90%E5%85%AC%E5%8F%B8"},"喆學家音樂文化有限公司":{"name":"喆學家音樂文化有限公司","id":"24673955","capital":2000000,"representative":"蘇_榮","address":"高雄市楠梓區德祥路130號1樓","aliases":[],"relationships":{"upstream":[],"downstream":[]},"webUrl":"https://tbdavid2019.github.io/taiwan-company-network/graph?company=%E5%96%86%E5%AD%B8%E5%AE%B6%E9%9F%B3%E6%A8%82%E6%96%87%E5%8C%96%E6%9C%89%E9%99%90%E5%85%AC%E5%8F%B8"},"喆暘科技有限公司":{"name":"喆暘科技有限公司","id":"24714317","capital":1000000,"representative":"林_超","address":"新北市汐止區建成路142巷19弄7號8樓","aliases":[],"relationships":{"upstream":[],"downstream":[]},"webUrl":"https://tbdavid2019.github.io/taiwan-company-network/graph?company=%E5%96%86%E6%9A%98%E7%A7%91%E6%8A%80%E6%9C%89%E9%99%90%E5%85%AC%E5%8F%B8"},"喆觀室內裝修設計有限公司":{"name":"喆觀室內裝修設計有限公司","id":"25073970","capital":1000000,"representative":"鄭_莉","address":"臺中市大甲區文武里德興路121號1樓","aliases":[],"relationships":{"upstream":[],"downstream":[]},"webUrl":"https://tbdavid2019.github.io/taiwan-company-network/graph?company=%E5%96%86%E8%A7%80%E5%AE%A4%E5%85%A7%E8%A3%9D%E4%BF%AE%E8%A8%AD%E8%A8%88%E6%9C%89%E9%99%90%E5%85%AC%E5%8F%B8"},"喆貿有限公司":{"name":"喆貿有限公司","id":"27486575","capital":500000,"representative":"莊_斐","address":"高雄市大寮區琉球路220號1樓","aliases":[],"relationships":{"upstream":[],"downstream":[]},"webUrl":"https://tbdavid2019.github.io/taiwan-company-network/graph?company=%E5%96%86%E8%B2%BF%E6%9C%89%E9%99%90%E5%85%AC%E5%8F%B8"},"喆南實業有限公司":{"name":"喆南實業有限公司","id":"28080118","capital":12000000,"representative":"張_雄","address":"桃園縣桃園市雲林里昆明路2之1號","aliases":[],"relationships":{"upstream":[],"downstream":[]},"webUrl":"https://tbdavid2019.github.io/taiwan-company-network/graph?company=%E5%96%86%E5%8D%97%E5%AF%A6%E6%A5%AD%E6%9C%89%E9%99%90%E5%85%AC%E5%8F%B8"},"喆聖實業有限公司":{"name":"喆聖實業有限公司","id":"28392148","capital":1000000,"representative":"王_翰","address":"新北市林口區仁愛路一段40號1樓","aliases":[],"relationships":{"upstream":[],"downstream":[]},"webUrl":"https://tbdavid2019.github.io/taiwan-company-network/graph?company=%E5%96%86%E8%81%96%E5%AF%A6%E6%A5%AD%E6%9C%89%E9%99%90%E5%85%AC%E5%8F%B8"},"喆鼎實業有限公司":{"name":"喆鼎實業有限公司","id":"28834411","capital":1000000,"representative":"黃_松","address":"臺北市中山區林森北路479號5樓之2","aliases":[],"relationships":{"upstream":[],"downstream":[]},"webUrl":"https://tbdavid2019.github.io/taiwan-company-network/graph?company=%E5%96%86%E9%BC%8E%E5%AF%A6%E6%A5%AD%E6%9C%89%E9%99%90%E5%85%AC%E5%8F%B8"},"喆星實業有限公司":{"name":"喆星實業有限公司","id":"30913453","capital":1000000,"representative":"曾_鳳","address":"臺北市大安區和平東路1段15號4樓","aliases":[],"relationships":{"upstream":[],"downstream":[]},"webUrl":"https://tbdavid2019.github.io/taiwan-company-network/graph?company=%E5%96%86%E6%98%9F%E5%AF%A6%E6%A5%AD%E6%9C%89%E9%99%90%E5%85%AC%E5%8F%B8"},"喆鴻國際有限公司":{"name":"喆鴻國際有限公司","id":"42616627","capital":3000000,"representative":"陳_蘭","address":"臺北市中正區公園路32號12樓","aliases":[],"relationships":{"upstream":[],"downstream":[]},"webUrl":"https://tbdavid2019.github.io/taiwan-company-network/graph?company=%E5%96%86%E9%B4%BB%E5%9C%8B%E9%9A%9B%E6%9C%89%E9%99%90%E5%85%AC%E5%8F%B8"},"喆鼎室內裝修設計企業有限公司":{"name":"喆鼎室內裝修設計企業有限公司","id":"42718146","capital":8500000,"representative":"黃_松","address":"新北市中和區連城路89巷30號地下一層","aliases":[],"relationships":{"upstream":[],"downstream":[]},"webUrl":"https://tbdavid2019.github.io/taiwan-company-network/graph?company=%E5%96%86%E9%BC%8E%E5%AE%A4%E5%85%A7%E8%A3%9D%E4%BF%AE%E8%A8%AD%E8%A8%88%E4%BC%81%E6%A5%AD%E6%9C%89%E9%99%90%E5%85%AC%E5%8F%B8"},"喆信有限公司":{"name":"喆信有限公司","id":"42807668","capital":3000000,"representative":"張_山","address":"高雄市三民區大順二路425巷13弄5號1樓","aliases":[],"relationships":{"upstream":[],"downstream":[]},"webUrl":"https://tbdavid2019.github.io/taiwan-company-network/graph?company=%E5%96%86%E4%BF%A1%E6%9C%89%E9%99%90%E5%85%AC%E5%8F%B8"},"喆也設計顧問股份有限公司":{"name":"喆也設計顧問股份有限公司","id":"42989528","capital":5000000,"representative":"姜_凌","address":"臺北市內湖區新明路317號7樓","aliases":[],"relationships":{"upstream":[],"downstream":[]},"webUrl":"https://tbdavid2019.github.io/taiwan-company-network/graph?company=%E5%96%86%E4%B9%9F%E8%A8%AD%E8%A8%88%E9%A1%A7%E5%95%8F%E8%82%A1%E4%BB%BD%E6%9C%89%E9%99%90%E5%85%AC%E5%8F%B8"},"喆祥投資股份有限公司":{"name":"喆祥投資股份有限公司","id":"42995253","capital":10000000,"representative":"盧_華","address":"臺北市大安區忠孝東路4段130號11樓","aliases":[],"relationships":{"upstream":[],"downstream":[]},"webUrl":"https://tbdavid2019.github.io/taiwan-company-network/graph?company=%E5%96%86%E7%A5%A5%E6%8A%95%E8%B3%87%E8%82%A1%E4%BB%BD%E6%9C%89%E9%99%90%E5%85%AC%E5%8F%B8"},"喆米餐飲有限公司":{"name":"喆米餐飲有限公司","id":"45877292","capital":5000000,"representative":"林_珍","address":"臺中市西區土庫里五權一街63之2號2樓","aliases":[],"relationships":{"upstream":[],"downstream":[]},"webUrl":"https://tbdavid2019.github.io/taiwan-company-network/graph?company=%E5%96%86%E7%B1%B3%E9%A4%90%E9%A3%B2%E6%9C%89%E9%99%90%E5%85%AC%E5%8F%B8"},"喆宇企業有限公司":{"name":"喆宇企業有限公司","id":"46410203","capital":1000000,"representative":"張_鈞","address":"新北市三重區明志街72號3樓","aliases":[],"relationships":{"upstream":[],"downstream":[]},"webUrl":"https://tbdavid2019.github.io/taiwan-company-network/graph?company=%E5%96%86%E5%AE%87%E4%BC%81%E6%A5%AD%E6%9C%89%E9%99%90%E5%85%AC%E5%8F%B8"},"喆硯國際有限公司":{"name":"喆硯國際有限公司","id":"50839930","capital":500000,"representative":"黃_聖","address":"臺中市西屯區福科路961巷66號1樓","aliases":[],"relationships":{"upstream":[],"downstream":[]},"webUrl":"https://tbdavid2019.github.io/taiwan-company-network/graph?company=%E5%96%86%E7%A1%AF%E5%9C%8B%E9%9A%9B%E6%9C%89%E9%99%90%E5%85%AC%E5%8F%B8"},"喆璽不動產仲介經紀有限公司":{"name":"喆璽不動產仲介經紀有限公司","id":"50923373","capital":6210000,"representative":"趙_君","address":"桃園市桃園區大興西路二段107號、107號2樓","aliases":[],"relationships":{"upstream":[],"downstream":[]},"webUrl":"https://tbdavid2019.github.io/taiwan-company-network/graph?company=%E5%96%86%E7%92%BD%E4%B8%8D%E5%8B%95%E7%94%A2%E4%BB%B2%E4%BB%8B%E7%B6%93%E7%B4%80%E6%9C%89%E9%99%90%E5%85%AC%E5%8F%B8"},"喆源工程有限公司":{"name":"喆源工程有限公司","id":"50993089","capital":500000,"representative":"楊_芬","address":"新北市土城區大暖路53之2號  ","aliases":[],"relationships":{"upstream":[],"downstream":[]},"webUrl":"https://tbdavid2019.github.io/taiwan-company-network/graph?company=%E5%96%86%E6%BA%90%E5%B7%A5%E7%A8%8B%E6%9C%89%E9%99%90%E5%85%AC%E5%8F%B8"},"喆安重機械有限公司":{"name":"喆安重機械有限公司","id":"53133367","capital":6300000,"representative":"許_安","address":"高雄市阿蓮區中正路216巷17號1樓  ","aliases":[],"relationships":{"upstream":[],"downstream":[]},"webUrl":"https://tbdavid2019.github.io/taiwan-company-network/graph?company=%E5%96%86%E5%AE%89%E9%87%8D%E6%A9%9F%E6%A2%B0%E6%9C%89%E9%99%90%E5%85%AC%E5%8F%B8"},"喆成國際工程有限公司":{"name":"喆成國際工程有限公司","id":"53296621","capital":5588000,"representative":"方_英","address":"桃園市平鎮區湧安里湧安路19號9樓","aliases":[],"relationships":{"upstream":[],"downstream":[]},"webUrl":"https://tbdavid2019.github.io/taiwan-company-network/graph?company=%E5%96%86%E6%88%90%E5%9C%8B%E9%9A%9B%E5%B7%A5%E7%A8%8B%E6%9C%89%E9%99%90%E5%85%AC%E5%8F%B8"},"喆璽開發建設有限公司":{"name":"喆璽開發建設有限公司","id":"53495213","capital":3000000,"representative":"盧_諺","address":"臺中市東區精武路157號4樓之1","aliases":[],"relationships":{"upstream":[],"downstream":[]},"webUrl":"https://tbdavid2019.github.io/taiwan-company-network/graph?company=%E5%96%86%E7%92%BD%E9%96%8B%E7%99%BC%E5%BB%BA%E8%A8%AD%E6%9C%89%E9%99%90%E5%85%AC%E5%8F%B8"},"喆美工程有限公司":{"name":"喆美工程有限公司","id":"53518779","capital":10000000,"representative":"陳_富","address":"苗栗縣竹南鎮聖福里13鄰環市路三段139號","aliases":[],"relationships":{"upstream":[],"downstream":[]},"webUrl":"https://tbdavid2019.github.io/taiwan-company-network/graph?company=%E5%96%86%E7%BE%8E%E5%B7%A5%E7%A8%8B%E6%9C%89%E9%99%90%E5%85%AC%E5%8F%B8"},"喆喬廣告行銷有限公司":{"name":"喆喬廣告行銷有限公司","id":"53585164","capital":1000000,"representative":"陳_香","address":"高雄市小港區高坪二十三路117巷9號2樓","aliases":[],"relationships":{"upstream":[],"downstream":[]},"webUrl":"https://tbdavid2019.github.io/taiwan-company-network/graph?company=%E5%96%86%E5%96%AC%E5%BB%A3%E5%91%8A%E8%A1%8C%E9%8A%B7%E6%9C%89%E9%99%90%E5%85%AC%E5%8F%B8"},"喆安精密有限公司":{"name":"喆安精密有限公司","id":"53642572","capital":5000000,"representative":"馬_吉","address":"新竹縣湖口鄉湖口村祥喜路209號","aliases":[],"relationships":{"upstream":[],"downstream":[]},"webUrl":"https://tbdavid2019.github.io/taiwan-company-network/graph?company=%E5%96%86%E5%AE%89%E7%B2%BE%E5%AF%86%E6%9C%89%E9%99%90%E5%85%AC%E5%8F%B8"},"喆禮不動產仲介經紀有限公司":{"name":"喆禮不動產仲介經紀有限公司","id":"53823172","capital":1000000,"representative":"趙_君","address":"桃園市桃園區永安路501號","aliases":[],"relationships":{"upstream":[],"downstream":[]},"webUrl":"https://tbdavid2019.github.io/taiwan-company-network/graph?company=%E5%96%86%E7%A6%AE%E4%B8%8D%E5%8B%95%E7%94%A2%E4%BB%B2%E4%BB%8B%E7%B6%93%E7%B4%80%E6%9C%89%E9%99%90%E5%85%AC%E5%8F%B8"},"喆丰股份有限公司":{"name":"喆丰股份有限公司","id":"53915593","capital":60000000,"representative":"施_芳","address":"桃園市蘆竹區內厝里長興路三段137巷42號","aliases":[],"relationships":{"upstream":["丰上工業股份有限公司","富美元嘉有限公司"],"downstream":[]},"webUrl":"https://tbdavid2019.github.io/taiwan-company-network/graph?company=%E5%96%86%E4%B8%B0%E8%82%A1%E4%BB%BD%E6%9C%89%E9%99%90%E5%85%AC%E5%8F%B8"},"喆能科技股份有限公司":{"name":"喆能科技股份有限公司","id":"54185588","capital":30000000,"representative":"廖_生","address":"新北市中和區板南路661號6樓","aliases":[],"relationships":{"upstream":[],"downstream":[]},"webUrl":"https://tbdavid2019.github.io/taiwan-company-network/graph?company=%E5%96%86%E8%83%BD%E7%A7%91%E6%8A%80%E8%82%A1%E4%BB%BD%E6%9C%89%E9%99%90%E5%85%AC%E5%8F%B8"},"喆寅投資有限公司":{"name":"喆寅投資有限公司","id":"54333722","capital":1000000,"representative":"陳_媗","address":"新北市泰山區工專路12巷19之1號","aliases":[],"relationships":{"upstream":[],"downstream":[]},"webUrl":"https://tbdavid2019.github.io/taiwan-company-network/graph?company=%E5%96%86%E5%AF%85%E6%8A%95%E8%B3%87%E6%9C%89%E9%99%90%E5%85%AC%E5%8F%B8"},"喆里空間設計有限公司":{"name":"喆里空間設計有限公司","id":"54711864","capital":300000,"representative":"簡_里","address":"新北市板橋區大觀路2段153巷46弄86號","aliases":[],"relationships":{"upstream":[],"downstream":[]},"webUrl":"https://tbdavid2019.github.io/taiwan-company-network/graph?company=%E5%96%86%E9%87%8C%E7%A9%BA%E9%96%93%E8%A8%AD%E8%A8%88%E6%9C%89%E9%99%90%E5%85%AC%E5%8F%B8"},"喆能科技工程有限公司":{"name":"喆能科技工程有限公司","id":"54734276","capital":5000000,"representative":"宋_蓉","address":"新北市汐止區復興路11號3樓之1","aliases":[],"relationships":{"upstream":[],"downstream":[]},"webUrl":"https://tbdavid2019.github.io/taiwan-company-network/graph?company=%E5%96%86%E8%83%BD%E7%A7%91%E6%8A%80%E5%B7%A5%E7%A8%8B%E6%9C%89%E9%99%90%E5%85%AC%E5%8F%B8"},"喆富創新科技股份有限公司":{"name":"喆富創新科技股份有限公司","id":"54778225","capital":200000000,"representative":"梁_成","address":"新竹市東區龍山里光復路一段472號6樓之七","aliases":[],"relationships":{"upstream":["喆鑫投資有限公司"],"downstream":["喆昊科技股份有限公司","晶亮芯科技股份有限公司"]},"webUrl":"https://tbdavid2019.github.io/taiwan-company-network/graph?company=%E5%96%86%E5%AF%8C%E5%89%B5%E6%96%B0%E7%A7%91%E6%8A%80%E8%82%A1%E4%BB%BD%E6%9C%89%E9%99%90%E5%85%AC%E5%8F%B8"},"喆光照明光電股份有限公司":{"name":"喆光照明光電股份有限公司","id":"54778294","capital":25000000,"representative":"武_芬","address":"新竹市龍山里7鄰光復路一段472號6樓之7","aliases":[],"relationships":{"upstream":[],"downstream":[]},"webUrl":"https://tbdavid2019.github.io/taiwan-company-network/graph?company=%E5%96%86%E5%85%89%E7%85%A7%E6%98%8E%E5%85%89%E9%9B%BB%E8%82%A1%E4%BB%BD%E6%9C%89%E9%99%90%E5%85%AC%E5%8F%B8"},"喆超有限公司":{"name":"喆超有限公司","id":"54888840","capital":500000,"representative":"巫_擇","address":"臺中市外埔區永豐里六分路72之32號1樓","aliases":[],"relationships":{"upstream":[],"downstream":[]},"webUrl":"https://tbdavid2019.github.io/taiwan-company-network/graph?company=%E5%96%86%E8%B6%85%E6%9C%89%E9%99%90%E5%85%AC%E5%8F%B8"},"喆作設計有限公司":{"name":"喆作設計有限公司","id":"56630418","capital":300000,"representative":"凃_騰","address":"宜蘭縣蘇澳鎮蘇東里4鄰蘇東路6之12號  ","aliases":[],"relationships":{"upstream":[],"downstream":[]},"webUrl":"https://tbdavid2019.github.io/taiwan-company-network/graph?company=%E5%96%86%E4%BD%9C%E8%A8%AD%E8%A8%88%E6%9C%89%E9%99%90%E5%85%AC%E5%8F%B8"},"喆澤國際有限公司":{"name":"喆澤國際有限公司","id":"56636406","capital":300000,"representative":"劉_中","address":"新竹縣竹北市竹仁里26鄰四維街164號1樓  ","aliases":[],"relationships":{"upstream":[],"downstream":[]},"webUrl":"https://tbdavid2019.github.io/taiwan-company-network/graph?company=%E5%96%86%E6%BE%A4%E5%9C%8B%E9%9A%9B%E6%9C%89%E9%99%90%E5%85%AC%E5%8F%B8"},"喆喆資訊行銷有限公司":{"name":"喆喆資訊行銷有限公司","id":"59332820","capital":600000,"representative":"劉_君","address":"高雄市新興區民生一路56號18樓之１","aliases":[],"relationships":{"upstream":[],"downstream":[]},"webUrl":"https://tbdavid2019.github.io/taiwan-company-network/graph?company=%E5%96%86%E5%96%86%E8%B3%87%E8%A8%8A%E8%A1%8C%E9%8A%B7%E6%9C%89%E9%99%90%E5%85%AC%E5%8F%B8"},"喆豐土地開發股份有限公司":{"name":"喆豐土地開發股份有限公司","id":"60230694","capital":65900000,"representative":"魏_蘭","address":"臺中市南屯區大川街50號6樓之3","aliases":[],"relationships":{"upstream":["新裕投資股份有限公司","新富銘建設股份有限公司"],"downstream":[]},"webUrl":"https://tbdavid2019.github.io/taiwan-company-network/graph?company=%E5%96%86%E8%B1%90%E5%9C%9F%E5%9C%B0%E9%96%8B%E7%99%BC%E8%82%A1%E4%BB%BD%E6%9C%89%E9%99%90%E5%85%AC%E5%8F%B8"},"喆盛石材有限公司":{"name":"喆盛石材有限公司","id":"60361442","capital":500000,"representative":"陳_玉","address":"臺中市西屯區美滿街17巷7號1樓  ","aliases":[],"relationships":{"upstream":[],"downstream":[]},"webUrl":"https://tbdavid2019.github.io/taiwan-company-network/graph?company=%E5%96%86%E7%9B%9B%E7%9F%B3%E6%9D%90%E6%9C%89%E9%99%90%E5%85%AC%E5%8F%B8"},"喆盛投資有限公司":{"name":"喆盛投資有限公司","id":"60420706","capital":29500000,"representative":"祁_傑","address":"臺中市豐原區南村里圓環東路703號11樓之2","aliases":[],"relationships":{"upstream":[],"downstream":[]},"webUrl":"https://tbdavid2019.github.io/taiwan-company-network/graph?company=%E5%96%86%E7%9B%9B%E6%8A%95%E8%B3%87%E6%9C%89%E9%99%90%E5%85%AC%E5%8F%B8"},"喆喆顧問有限公司":{"name":"喆喆顧問有限公司","id":"60436989","capital":10000,"representative":"吳_芳","address":"嘉義市西區湖內里健康十二路277號一樓","aliases":[],"relationships":{"upstream":[],"downstream":[]},"webUrl":"https://tbdavid2019.github.io/taiwan-company-network/graph?company=%E5%96%86%E5%96%86%E9%A1%A7%E5%95%8F%E6%9C%89%E9%99%90%E5%85%AC%E5%8F%B8"},"喆德新能源股份有限公司":{"name":"喆德新能源股份有限公司","id":"60574119","capital":1000000,"representative":"包_稷","address":"新北市新店區寶橋路235巷138號8樓","aliases":[],"relationships":{"upstream":["立德電子股份有限公司"],"downstream":[]},"webUrl":"https://tbdavid2019.github.io/taiwan-company-network/graph?company=%E5%96%86%E5%BE%B7%E6%96%B0%E8%83%BD%E6%BA%90%E8%82%A1%E4%BB%BD%E6%9C%89%E9%99%90%E5%85%AC%E5%8F%B8"},"喆元建設有限公司":{"name":"喆元建設有限公司","id":"60593875","capital":3000000,"representative":"陳_中","address":"臺北市中山區新生北路3段62巷2號","aliases":[],"relationships":{"upstream":[],"downstream":[]},"webUrl":"https://tbdavid2019.github.io/taiwan-company-network/graph?company=%E5%96%86%E5%85%83%E5%BB%BA%E8%A8%AD%E6%9C%89%E9%99%90%E5%85%AC%E5%8F%B8"},"喆哲企業股份有限公司":{"name":"喆哲企業股份有限公司","id":"60658546","capital":500000,"representative":"黃_倫","address":"新北市新店區民權路108號10樓","aliases":[],"relationships":{"upstream":[],"downstream":[]},"webUrl":"https://tbdavid2019.github.io/taiwan-company-network/graph?company=%E5%96%86%E5%93%B2%E4%BC%81%E6%A5%AD%E8%82%A1%E4%BB%BD%E6%9C%89%E9%99%90%E5%85%AC%E5%8F%B8"},"喆霖國際有限公司":{"name":"喆霖國際有限公司","id":"60658877","capital":100000,"representative":"游_霖","address":"新北市淡水區淡金路1段521號11樓","aliases":[],"relationships":{"upstream":[],"downstream":[]},"webUrl":"https://tbdavid2019.github.io/taiwan-company-network/graph?company=%E5%96%86%E9%9C%96%E5%9C%8B%E9%9A%9B%E6%9C%89%E9%99%90%E5%85%AC%E5%8F%B8"},"喆時國際開發有限公司":{"name":"喆時國際開發有限公司","id":"60662540","capital":1249000,"representative":"蔡_昀","address":"臺北市大安區羅斯福路3段125號12樓之4","aliases":[],"relationships":{"upstream":[],"downstream":[]},"webUrl":"https://tbdavid2019.github.io/taiwan-company-network/graph?company=%E5%96%86%E6%99%82%E5%9C%8B%E9%9A%9B%E9%96%8B%E7%99%BC%E6%9C%89%E9%99%90%E5%85%AC%E5%8F%B8"},"喆大車業有限公司":{"name":"喆大車業有限公司","id":"60724567","capital":3000000,"representative":"林_家","address":"臺南市東區仁和里利東街75號1樓","aliases":[],"relationships":{"upstream":[],"downstream":[]},"webUrl":"https://tbdavid2019.github.io/taiwan-company-network/graph?company=%E5%96%86%E5%A4%A7%E8%BB%8A%E6%A5%AD%E6%9C%89%E9%99%90%E5%85%AC%E5%8F%B8"},"喆和股份有限公司":{"name":"喆和股份有限公司","id":"62191004","capital":5000000,"representative":"王_喆","address":"新北市林口區公園路203號10樓之1至之2","aliases":[],"relationships":{"upstream":[],"downstream":[]},"webUrl":"https://tbdavid2019.github.io/taiwan-company-network/graph?company=%E5%96%86%E5%92%8C%E8%82%A1%E4%BB%BD%E6%9C%89%E9%99%90%E5%85%AC%E5%8F%B8"},"喆廬文化有限公司":{"name":"喆廬文化有限公司","id":"62255837","capital":200000,"representative":"詹_雅","address":"高雄市苓雅區家齊路43號6樓","aliases":[],"relationships":{"upstream":[],"downstream":[]},"webUrl":"https://tbdavid2019.github.io/taiwan-company-network/graph?company=%E5%96%86%E5%BB%AC%E6%96%87%E5%8C%96%E6%9C%89%E9%99%90%E5%85%AC%E5%8F%B8"},"喆田國際投資股份有限公司":{"name":"喆田國際投資股份有限公司","id":"63075817","capital":15000000,"representative":"黃_美","address":"臺中市西區向上路一段79巷16號3樓","aliases":[],"relationships":{"upstream":[],"downstream":[]},"webUrl":"https://tbdavid2019.github.io/taiwan-company-network/graph?company=%E5%96%86%E7%94%B0%E5%9C%8B%E9%9A%9B%E6%8A%95%E8%B3%87%E8%82%A1%E4%BB%BD%E6%9C%89%E9%99%90%E5%85%AC%E5%8F%B8"},"喆任實業有限公司":{"name":"喆任實業有限公司","id":"64168905","capital":100000,"representative":"洪_欣","address":"臺中市西屯區青海路二段361號7樓之3  ","aliases":[],"relationships":{"upstream":[],"downstream":[]},"webUrl":"https://tbdavid2019.github.io/taiwan-company-network/graph?company=%E5%96%86%E4%BB%BB%E5%AF%A6%E6%A5%AD%E6%9C%89%E9%99%90%E5%85%AC%E5%8F%B8"},"喆康國際有限公司":{"name":"喆康國際有限公司","id":"69283658","capital":300000,"representative":"鍾_瑋","address":"高雄市鼓山區南屏路855號17樓之2","aliases":[],"relationships":{"upstream":[],"downstream":[]},"webUrl":"https://tbdavid2019.github.io/taiwan-company-network/graph?company=%E5%96%86%E5%BA%B7%E5%9C%8B%E9%9A%9B%E6%9C%89%E9%99%90%E5%85%AC%E5%8F%B8"},"喆明國際有限公司":{"name":"喆明國際有限公司","id":"69412230","capital":1000000,"representative":"張_菊","address":"臺北市大安區忠孝東路4段169號11樓之4","aliases":[],"relationships":{"upstream":[],"downstream":[]},"webUrl":"https://tbdavid2019.github.io/taiwan-company-network/graph?company=%E5%96%86%E6%98%8E%E5%9C%8B%E9%9A%9B%E6%9C%89%E9%99%90%E5%85%AC%E5%8F%B8"},"喆葒有限公司":{"name":"喆葒有限公司","id":"69723852","capital":1000000,"representative":"陳_文","address":"桃園市大溪區民權路14號1樓","aliases":[],"relationships":{"upstream":[],"downstream":[]},"webUrl":"https://tbdavid2019.github.io/taiwan-company-network/graph?company=%E5%96%86%E8%91%92%E6%9C%89%E9%99%90%E5%85%AC%E5%8F%B8"},"喆順企業有限公司":{"name":"喆順企業有限公司","id":"70446223","capital":6000000,"representative":"謝_萍","address":"臺北市信義區虎林街235號7樓","aliases":[],"relationships":{"upstream":[],"downstream":[]},"webUrl":"https://tbdavid2019.github.io/taiwan-company-network/graph?company=%E5%96%86%E9%A0%86%E4%BC%81%E6%A5%AD%E6%9C%89%E9%99%90%E5%85%AC%E5%8F%B8"},"喆凱五金有限公司":{"name":"喆凱五金有限公司","id":"70697543","capital":1000000,"representative":"李_園","address":"臺中市東區樂業路188巷33號","aliases":[],"relationships":{"upstream":[],"downstream":[]},"webUrl":"https://tbdavid2019.github.io/taiwan-company-network/graph?company=%E5%96%86%E5%87%B1%E4%BA%94%E9%87%91%E6%9C%89%E9%99%90%E5%85%AC%E5%8F%B8"},"喆威實業有限公司":{"name":"喆威實業有限公司","id":"80047858","capital":10000000,"representative":"任_遠","address":"臺北市大安區光復南路696號12樓之2  ","aliases":[],"relationships":{"upstream":[],"downstream":[]},"webUrl":"https://tbdavid2019.github.io/taiwan-company-network/graph?company=%E5%96%86%E5%A8%81%E5%AF%A6%E6%A5%AD%E6%9C%89%E9%99%90%E5%85%AC%E5%8F%B8"},"喆元實業有限公司":{"name":"喆元實業有限公司","id":"80207398","capital":5000000,"representative":"蔡_任","address":"臺中市北屯區和平里軍功東街37號2樓","aliases":[],"relationships":{"upstream":[],"downstream":[]},"webUrl":"https://tbdavid2019.github.io/taiwan-company-network/graph?company=%E5%96%86%E5%85%83%E5%AF%A6%E6%A5%AD%E6%9C%89%E9%99%90%E5%85%AC%E5%8F%B8"},"喆昇企業有限公司":{"name":"喆昇企業有限公司","id":"80479969","capital":10000000,"representative":"何_哲","address":"雲林縣斗六市榴南里斗工二路86號","aliases":[],"relationships":{"upstream":[],"downstream":[]},"webUrl":"https://tbdavid2019.github.io/taiwan-company-network/graph?company=%E5%96%86%E6%98%87%E4%BC%81%E6%A5%AD%E6%9C%89%E9%99%90%E5%85%AC%E5%8F%B8"},"喆順開發建設有限公司":{"name":"喆順開發建設有限公司","id":"80585928","capital":1000000,"representative":"徐_永","address":"桃園市中壢區中山東路一段161號","aliases":[],"relationships":{"upstream":[],"downstream":[]},"webUrl":"https://tbdavid2019.github.io/taiwan-company-network/graph?company=%E5%96%86%E9%A0%86%E9%96%8B%E7%99%BC%E5%BB%BA%E8%A8%AD%E6%9C%89%E9%99%90%E5%85%AC%E5%8F%B8"},"喆日不動產有限公司":{"name":"喆日不動產有限公司","id":"82978049","capital":3000000,"representative":"李_足","address":"臺北市中山區松江路97巷25號1樓","aliases":[],"relationships":{"upstream":[],"downstream":[]},"webUrl":"https://tbdavid2019.github.io/taiwan-company-network/graph?company=%E5%96%86%E6%97%A5%E4%B8%8D%E5%8B%95%E7%94%A2%E6%9C%89%E9%99%90%E5%85%AC%E5%8F%B8"},"喆亮有限公司":{"name":"喆亮有限公司","id":"83000337","capital":3500000,"representative":"蔡_瀅","address":"臺北市中山區長春路20號4樓之3","aliases":[],"relationships":{"upstream":[],"downstream":[]},"webUrl":"https://tbdavid2019.github.io/taiwan-company-network/graph?company=%E5%96%86%E4%BA%AE%E6%9C%89%E9%99%90%E5%85%AC%E5%8F%B8"},"喆家營造工程有限公司":{"name":"喆家營造工程有限公司","id":"83027440","capital":5600000,"representative":"李_卿","address":"基隆市中正區義一路87號3樓之1","aliases":[],"relationships":{"upstream":["華騏建築經理股份有限公司"],"downstream":[]},"webUrl":"https://tbdavid2019.github.io/taiwan-company-network/graph?company=%E5%96%86%E5%AE%B6%E7%87%9F%E9%80%A0%E5%B7%A5%E7%A8%8B%E6%9C%89%E9%99%90%E5%85%AC%E5%8F%B8"},"喆聚有限公司":{"name":"喆聚有限公司","id":"83027568","capital":500000,"representative":"蔡_諠","address":"新竹市北區金竹路136號7樓之2","aliases":[],"relationships":{"upstream":[],"downstream":[]},"webUrl":"https://tbdavid2019.github.io/taiwan-company-network/graph?company=%E5%96%86%E8%81%9A%E6%9C%89%E9%99%90%E5%85%AC%E5%8F%B8"},"喆安設計有限公司":{"name":"喆安設計有限公司","id":"83037215","capital":1000000,"representative":"張_洲","address":"臺北市信義區基隆路1段131號8樓之9","aliases":[],"relationships":{"upstream":[],"downstream":[]},"webUrl":"https://tbdavid2019.github.io/taiwan-company-network/graph?company=%E5%96%86%E5%AE%89%E8%A8%AD%E8%A8%88%E6%9C%89%E9%99%90%E5%85%AC%E5%8F%B8"},"喆日設計有限公司":{"name":"喆日設計有限公司","id":"83067006","capital":500000,"representative":"吳_儒","address":"臺中市北屯區平田里遼寧路一段23號","aliases":[],"relationships":{"upstream":[],"downstream":[]},"webUrl":"https://tbdavid2019.github.io/taiwan-company-network/graph?company=%E5%96%86%E6%97%A5%E8%A8%AD%E8%A8%88%E6%9C%89%E9%99%90%E5%85%AC%E5%8F%B8"},"喆鑫投資有限公司":{"name":"喆鑫投資有限公司","id":"83112608","capital":29000000,"representative":"武_芬","address":"新竹縣竹東鎮自強路1號","aliases":[],"relationships":{"upstream":[],"downstream":["喆富創新科技股份有限公司","喆昊科技股份有限公司","晶亮芯科技股份有限公司"]},"webUrl":"https://tbdavid2019.github.io/taiwan-company-network/graph?company=%E5%96%86%E9%91%AB%E6%8A%95%E8%B3%87%E6%9C%89%E9%99%90%E5%85%AC%E5%8F%B8"},"喆恩昊威有限公司":{"name":"喆恩昊威有限公司","id":"83274899","capital":1000000,"representative":"陳_宇","address":"桃園市大園區北港里自立二街25之5號2樓之1","aliases":[],"relationships":{"upstream":[],"downstream":[]},"webUrl":"https://tbdavid2019.github.io/taiwan-company-network/graph?company=%E5%96%86%E6%81%A9%E6%98%8A%E5%A8%81%E6%9C%89%E9%99%90%E5%85%AC%E5%8F%B8"},"喆舜品物股份有限公司":{"name":"喆舜品物股份有限公司","id":"83390715","capital":500000,"representative":"許_堯","address":"嘉義縣中埔鄉富收村興化廍46-9號1樓","aliases":[],"relationships":{"upstream":[],"downstream":[]},"webUrl":"https://tbdavid2019.github.io/taiwan-company-network/graph?company=%E5%96%86%E8%88%9C%E5%93%81%E7%89%A9%E8%82%A1%E4%BB%BD%E6%9C%89%E9%99%90%E5%85%AC%E5%8F%B8"},"喆洛國際股份有限公司":{"name":"喆洛國際股份有限公司","id":"83431820","capital":1800000,"representative":"陳_豪","address":"臺中市西屯區福和里臺灣大道四段925號19樓之1","aliases":[],"relationships":{"upstream":[],"downstream":[]},"webUrl":"https://tbdavid2019.github.io/taiwan-company-network/graph?company=%E5%96%86%E6%B4%9B%E5%9C%8B%E9%9A%9B%E8%82%A1%E4%BB%BD%E6%9C%89%E9%99%90%E5%85%AC%E5%8F%B8"},"喆時資本股份有限公司":{"name":"喆時資本股份有限公司","id":"83598074","capital":10000000,"representative":"鄭_福","address":"臺北市松山區南京東路4段 77號9樓之1","aliases":[],"relationships":{"upstream":["川石投資股份有限公司"],"downstream":[]},"webUrl":"https://tbdavid2019.github.io/taiwan-company-network/graph?company=%E5%96%86%E6%99%82%E8%B3%87%E6%9C%AC%E8%82%A1%E4%BB%BD%E6%9C%89%E9%99%90%E5%85%AC%E5%8F%B8"},"喆盟晟水電材料有限公司":{"name":"喆盟晟水電材料有限公司","id":"84594147","capital":5000000,"representative":"梁_英","address":"高雄市大寮區興中街96號  ","aliases":[],"relationships":{"upstream":[],"downstream":[]},"webUrl":"https://tbdavid2019.github.io/taiwan-company-network/graph?company=%E5%96%86%E7%9B%9F%E6%99%9F%E6%B0%B4%E9%9B%BB%E6%9D%90%E6%96%99%E6%9C%89%E9%99%90%E5%85%AC%E5%8F%B8"},"喆晟工業有限公司":{"name":"喆晟工業有限公司","id":"84672059","capital":8000000,"representative":"李_義","address":"新北市五股區水碓三路133號","aliases":[],"relationships":{"upstream":[],"downstream":[]},"webUrl":"https://tbdavid2019.github.io/taiwan-company-network/graph?company=%E5%96%86%E6%99%9F%E5%B7%A5%E6%A5%AD%E6%9C%89%E9%99%90%E5%85%AC%E5%8F%B8"},"喆雅國際有限公司":{"name":"喆雅國際有限公司","id":"84912924","capital":5000000,"representative":"戴_桂","address":"臺北市大安區大安路1段197號1樓","aliases":[],"relationships":{"upstream":[],"downstream":[]},"webUrl":"https://tbdavid2019.github.io/taiwan-company-network/graph?company=%E5%96%86%E9%9B%85%E5%9C%8B%E9%9A%9B%E6%9C%89%E9%99%90%E5%85%AC%E5%8F%B8"},"喆青空間設計有限公司":{"name":"喆青空間設計有限公司","id":"85046864","capital":200000,"representative":"許_淵","address":"臺北市中山區龍江路342巷31號5樓","aliases":[],"relationships":{"upstream":[],"downstream":[]},"webUrl":"https://tbdavid2019.github.io/taiwan-company-network/graph?company=%E5%96%86%E9%9D%92%E7%A9%BA%E9%96%93%E8%A8%AD%E8%A8%88%E6%9C%89%E9%99%90%E5%85%AC%E5%8F%B8"},"喆鼎有限公司":{"name":"喆鼎有限公司","id":"86061309","capital":5000000,"representative":"朱_隆","address":"高雄市前鎮區瑞和街47巷5之2號","aliases":[],"relationships":{"upstream":[],"downstream":[]},"webUrl":"https://tbdavid2019.github.io/taiwan-company-network/graph?company=%E5%96%86%E9%BC%8E%E6%9C%89%E9%99%90%E5%85%AC%E5%8F%B8"},"喆昌工程顧問有限公司":{"name":"喆昌工程顧問有限公司","id":"86139778","capital":2000000,"representative":"陳_喆","address":"臺北市松山區南京東路4段75巷20號4樓","aliases":[],"relationships":{"upstream":[],"downstream":[]},"webUrl":"https://tbdavid2019.github.io/taiwan-company-network/graph?company=%E5%96%86%E6%98%8C%E5%B7%A5%E7%A8%8B%E9%A1%A7%E5%95%8F%E6%9C%89%E9%99%90%E5%85%AC%E5%8F%B8"},"喆瑞科技有限公司":{"name":"喆瑞科技有限公司","id":"89409661","capital":10000000,"representative":"黃_臨","address":"高雄市三民區九如一路502號19樓之1","aliases":[],"relationships":{"upstream":[],"downstream":[]},"webUrl":"https://tbdavid2019.github.io/taiwan-company-network/graph?company=%E5%96%86%E7%91%9E%E7%A7%91%E6%8A%80%E6%9C%89%E9%99%90%E5%85%AC%E5%8F%B8"},"喆揚實業有限公司":{"name":"喆揚實業有限公司","id":"89478857","capital":5000000,"representative":"任_瑜","address":"新北市永和區中興街六九號","aliases":[],"relationships":{"upstream":[],"downstream":[]},"webUrl":"https://tbdavid2019.github.io/taiwan-company-network/graph?company=%E5%96%86%E6%8F%9A%E5%AF%A6%E6%A5%AD%E6%9C%89%E9%99%90%E5%85%AC%E5%8F%B8"},"喆豐開發有限公司":{"name":"喆豐開發有限公司","id":"90040931","capital":1000000,"representative":"張_弘","address":"新北市三重區三和路3段109號8樓之7","aliases":[],"relationships":{"upstream":[],"downstream":[]},"webUrl":"https://tbdavid2019.github.io/taiwan-company-network/graph?company=%E5%96%86%E8%B1%90%E9%96%8B%E7%99%BC%E6%9C%89%E9%99%90%E5%85%AC%E5%8F%B8"},"喆宇智能科技有限公司":{"name":"喆宇智能科技有限公司","id":"90054049","capital":5000000,"representative":"賴_宇","address":"新北市林口區中山路560號3樓之6","aliases":[],"relationships":{"upstream":[],"downstream":[]},"webUrl":"https://tbdavid2019.github.io/taiwan-company-network/graph?company=%E5%96%86%E5%AE%87%E6%99%BA%E8%83%BD%E7%A7%91%E6%8A%80%E6%9C%89%E9%99%90%E5%85%AC%E5%8F%B8"},"喆朵有限公司":{"name":"喆朵有限公司","id":"90255756","capital":700000,"representative":"曾_彥","address":"新竹縣竹東鎮龍鳳路30之5號7樓","aliases":[],"relationships":{"upstream":[],"downstream":[]},"webUrl":"https://tbdavid2019.github.io/taiwan-company-network/graph?company=%E5%96%86%E6%9C%B5%E6%9C%89%E9%99%90%E5%85%AC%E5%8F%B8"},"喆川國際塗裝美學有限公司":{"name":"喆川國際塗裝美學有限公司","id":"90304692","capital":2000000,"representative":"施_滄","address":"桃園市桃園區同德里中正路1095之1號13樓","aliases":[],"relationships":{"upstream":[],"downstream":[]},"webUrl":"https://tbdavid2019.github.io/taiwan-company-network/graph?company=%E5%96%86%E5%B7%9D%E5%9C%8B%E9%9A%9B%E5%A1%97%E8%A3%9D%E7%BE%8E%E5%AD%B8%E6%9C%89%E9%99%90%E5%85%AC%E5%8F%B8"},"喆吉工程有限公司":{"name":"喆吉工程有限公司","id":"90387757","capital":100000,"representative":"鍾_聖","address":"臺中市西區民生里自由路一段101號8樓之2","aliases":[],"relationships":{"upstream":[],"downstream":[]},"webUrl":"https://tbdavid2019.github.io/taiwan-company-network/graph?company=%E5%96%86%E5%90%89%E5%B7%A5%E7%A8%8B%E6%9C%89%E9%99%90%E5%85%AC%E5%8F%B8"},"喆威資產評估顧問有限公司":{"name":"喆威資產評估顧問有限公司","id":"90410912","capital":300000,"representative":"馬_威","address":"臺北市大安區仁愛路4段107號7樓","aliases":[],"relationships":{"upstream":[],"downstream":[]},"webUrl":"https://tbdavid2019.github.io/taiwan-company-network/graph?company=%E5%96%86%E5%A8%81%E8%B3%87%E7%94%A2%E8%A9%95%E4%BC%B0%E9%A1%A7%E5%95%8F%E6%9C%89%E9%99%90%E5%85%AC%E5%8F%B8"},"喆昱投資股份有限公司":{"name":"喆昱投資股份有限公司","id":"90444069","capital":20000000,"representative":"陳_興","address":"臺中市北屯區平德里文昌東五街16號1樓","aliases":[],"relationships":{"upstream":[],"downstream":["衡昱電商股份有限公司"]},"webUrl":"https://tbdavid2019.github.io/taiwan-company-network/graph?company=%E5%96%86%E6%98%B1%E6%8A%95%E8%B3%87%E8%82%A1%E4%BB%BD%E6%9C%89%E9%99%90%E5%85%AC%E5%8F%B8"},"喆垣設計室內裝修有限公司":{"name":"喆垣設計室內裝修有限公司","id":"90445145","capital":150000,"representative":"鍾_翰","address":"臺北市大安區安和路2段5號2樓","aliases":[],"relationships":{"upstream":[],"downstream":[]},"webUrl":"https://tbdavid2019.github.io/taiwan-company-network/graph?company=%E5%96%86%E5%9E%A3%E8%A8%AD%E8%A8%88%E5%AE%A4%E5%85%A7%E8%A3%9D%E4%BF%AE%E6%9C%89%E9%99%90%E5%85%AC%E5%8F%B8"},"喆盛寶投資股份有限公司":{"name":"喆盛寶投資股份有限公司","id":"90506748","capital":3000000,"representative":"劉_豪","address":"新北市永和區秀安街6號(1樓)","aliases":[],"relationships":{"upstream":[],"downstream":[]},"webUrl":"https://tbdavid2019.github.io/taiwan-company-network/graph?company=%E5%96%86%E7%9B%9B%E5%AF%B6%E6%8A%95%E8%B3%87%E8%82%A1%E4%BB%BD%E6%9C%89%E9%99%90%E5%85%AC%E5%8F%B8"},"喆叄室內設計有限公司":{"name":"喆叄室內設計有限公司","id":"90580633","capital":100000,"representative":"許_容","address":"桃園市桃園區正光一街110號","aliases":[],"relationships":{"upstream":[],"downstream":[]},"webUrl":"https://tbdavid2019.github.io/taiwan-company-network/graph?company=%E5%96%86%E5%8F%84%E5%AE%A4%E5%85%A7%E8%A8%AD%E8%A8%88%E6%9C%89%E9%99%90%E5%85%AC%E5%8F%B8"},"喆鑫資源整合環保有限公司":{"name":"喆鑫資源整合環保有限公司","id":"90593834","capital":500000,"representative":"許_雅","address":"屏東縣屏東市中正里莊敬街二段110巷30號1樓","aliases":[],"relationships":{"upstream":[],"downstream":[]},"webUrl":"https://tbdavid2019.github.io/taiwan-company-network/graph?company=%E5%96%86%E9%91%AB%E8%B3%87%E6%BA%90%E6%95%B4%E5%90%88%E7%92%B0%E4%BF%9D%E6%9C%89%E9%99%90%E5%85%AC%E5%8F%B8"},"喆同有限公司":{"name":"喆同有限公司","id":"90596847","capital":50000,"representative":"吳_喆","address":"新北市三重區重陽路3段5巷20號","aliases":[],"relationships":{"upstream":[],"downstream":[]},"webUrl":"https://tbdavid2019.github.io/taiwan-company-network/graph?company=%E5%96%86%E5%90%8C%E6%9C%89%E9%99%90%E5%85%AC%E5%8F%B8"},"喆仁廣告有限公司":{"name":"喆仁廣告有限公司","id":"90665344","capital":500000,"representative":"鄭_信","address":"臺北市中山區長春路348之5號5樓","aliases":[],"relationships":{"upstream":[],"downstream":[]},"webUrl":"https://tbdavid2019.github.io/taiwan-company-network/graph?company=%E5%96%86%E4%BB%81%E5%BB%A3%E5%91%8A%E6%9C%89%E9%99%90%E5%85%AC%E5%8F%B8"},"喆雍餐飲顧問有限公司":{"name":"喆雍餐飲顧問有限公司","id":"90667602","capital":300000,"representative":"周_卉","address":"臺北市大安區忠孝東路4段148號6樓","aliases":[],"relationships":{"upstream":[],"downstream":[]},"webUrl":"https://tbdavid2019.github.io/taiwan-company-network/graph?company=%E5%96%86%E9%9B%8D%E9%A4%90%E9%A3%B2%E9%A1%A7%E5%95%8F%E6%9C%89%E9%99%90%E5%85%AC%E5%8F%B8"},"喆晟空間設計工程有限公司":{"name":"喆晟空間設計工程有限公司","id":"90684834","capital":500000,"representative":"林_棠","address":"高雄市三民區博愛一路287號5樓","aliases":[],"relationships":{"upstream":[],"downstream":[]},"webUrl":"https://tbdavid2019.github.io/taiwan-company-network/graph?company=%E5%96%86%E6%99%9F%E7%A9%BA%E9%96%93%E8%A8%AD%E8%A8%88%E5%B7%A5%E7%A8%8B%E6%9C%89%E9%99%90%E5%85%AC%E5%8F%B8"},"喆木室內裝修有限公司":{"name":"喆木室內裝修有限公司","id":"90686946","capital":1000000,"representative":"吳_怡","address":"臺中市南區南平路33之2號5樓","aliases":[],"relationships":{"upstream":[],"downstream":[]},"webUrl":"https://tbdavid2019.github.io/taiwan-company-network/graph?company=%E5%96%86%E6%9C%A8%E5%AE%A4%E5%85%A7%E8%A3%9D%E4%BF%AE%E6%9C%89%E9%99%90%E5%85%AC%E5%8F%B8"},"喆群有限公司":{"name":"喆群有限公司","id":"90729797","capital":1388000,"representative":"許_榮","address":"新北市中和區連城路127巷3號","aliases":[],"relationships":{"upstream":[],"downstream":[]},"webUrl":"https://tbdavid2019.github.io/taiwan-company-network/graph?company=%E5%96%86%E7%BE%A4%E6%9C%89%E9%99%90%E5%85%AC%E5%8F%B8"},"喆富開發有限公司":{"name":"喆富開發有限公司","id":"90789464","capital":5000000,"representative":"金_司","address":"新竹市東區北大路40巷9之1號","aliases":[],"relationships":{"upstream":[],"downstream":[]},"webUrl":"https://tbdavid2019.github.io/taiwan-company-network/graph?company=%E5%96%86%E5%AF%8C%E9%96%8B%E7%99%BC%E6%9C%89%E9%99%90%E5%85%AC%E5%8F%B8"},"喆寓資產管理股份有限公司":{"name":"喆寓資產管理股份有限公司","id":"90897581","capital":0,"representative":"湯_儀","address":"臺北市中山區八德路2段245號11樓","aliases":[],"relationships":{"upstream":[],"downstream":[]},"webUrl":"https://tbdavid2019.github.io/taiwan-company-network/graph?company=%E5%96%86%E5%AF%93%E8%B3%87%E7%94%A2%E7%AE%A1%E7%90%86%E8%82%A1%E4%BB%BD%E6%9C%89%E9%99%90%E5%85%AC%E5%8F%B8"},"喆晟股份有限公司":{"name":"喆晟股份有限公司","id":"91090705","capital":7500000,"representative":"劉_奇","address":"新北市三重區五華街7巷87號","aliases":[],"relationships":{"upstream":[],"downstream":[]},"webUrl":"https://tbdavid2019.github.io/taiwan-company-network/graph?company=%E5%96%86%E6%99%9F%E8%82%A1%E4%BB%BD%E6%9C%89%E9%99%90%E5%85%AC%E5%8F%B8"},"喆群實業有限公司":{"name":"喆群實業有限公司","id":"91091057","capital":10000000,"representative":"李_雲","address":"新北市板橋區信義路235之10號2樓","aliases":[],"relationships":{"upstream":[],"downstream":[]},"webUrl":"https://tbdavid2019.github.io/taiwan-company-network/graph?company=%E5%96%86%E7%BE%A4%E5%AF%A6%E6%A5%AD%E6%9C%89%E9%99%90%E5%85%AC%E5%8F%B8"},"喆相有限公司":{"name":"喆相有限公司","id":"91122615","capital":4000000,"representative":"連_琪","address":"新竹縣竹北市高鐵七路65號14樓之7","aliases":[],"relationships":{"upstream":[],"downstream":[]},"webUrl":"https://tbdavid2019.github.io/taiwan-company-network/graph?company=%E5%96%86%E7%9B%B8%E6%9C%89%E9%99%90%E5%85%AC%E5%8F%B8"},"喆日貿易有限公司":{"name":"喆日貿易有限公司","id":"93527015","capital":200000,"representative":"洪_軒","address":"金門縣烈嶼鄉西口村湖井頭12-1號","aliases":[],"relationships":{"upstream":[],"downstream":[]},"webUrl":"https://tbdavid2019.github.io/taiwan-company-network/graph?company=%E5%96%86%E6%97%A5%E8%B2%BF%E6%98%93%E6%9C%89%E9%99%90%E5%85%AC%E5%8F%B8"},"喆安事業有限公司":{"name":"喆安事業有限公司","id":"93638949","capital":400000,"representative":"許_隆","address":"臺中市大雅區文雅里中清路三段997巷19號3樓","aliases":[],"relationships":{"upstream":[],"downstream":[]},"webUrl":"https://tbdavid2019.github.io/taiwan-company-network/graph?company=%E5%96%86%E5%AE%89%E4%BA%8B%E6%A5%AD%E6%9C%89%E9%99%90%E5%85%AC%E5%8F%B8"},"喆勝國際有限公司":{"name":"喆勝國際有限公司","id":"94011917","capital":300000,"representative":"饒_琳","address":"桃園市桃園區寶慶路508之1號11樓","aliases":[],"relationships":{"upstream":[],"downstream":[]},"webUrl":"https://tbdavid2019.github.io/taiwan-company-network/graph?company=%E5%96%86%E5%8B%9D%E5%9C%8B%E9%9A%9B%E6%9C%89%E9%99%90%E5%85%AC%E5%8F%B8"},"喆創企業有限公司":{"name":"喆創企業有限公司","id":"94024912","capital":1000000,"representative":"高_忠","address":"桃園市桃園區大興西路2段61號11樓","aliases":[],"relationships":{"upstream":[],"downstream":["喆新展業股份有限公司"]},"webUrl":"https://tbdavid2019.github.io/taiwan-company-network/graph?company=%E5%96%86%E5%89%B5%E4%BC%81%E6%A5%AD%E6%9C%89%E9%99%90%E5%85%AC%E5%8F%B8"},"喆漢有限公司":{"name":"喆漢有限公司","id":"94077380","capital":500000,"representative":"徐_漢","address":"高雄市左營區重惠街212號1樓","aliases":[],"relationships":{"upstream":[],"downstream":[]},"webUrl":"https://tbdavid2019.github.io/taiwan-company-network/graph?company=%E5%96%86%E6%BC%A2%E6%9C%89%E9%99%90%E5%85%AC%E5%8F%B8"},"喆華原住民企業有限公司":{"name":"喆華原住民企業有限公司","id":"94091783","capital":30000,"representative":"曾_達","address":"桃園市蘆竹區南崁路一段83號18樓之3","aliases":[],"relationships":{"upstream":[],"downstream":[]},"webUrl":"https://tbdavid2019.github.io/taiwan-company-network/graph?company=%E5%96%86%E8%8F%AF%E5%8E%9F%E4%BD%8F%E6%B0%91%E4%BC%81%E6%A5%AD%E6%9C%89%E9%99%90%E5%85%AC%E5%8F%B8"},"喆喆生活企業有限公司":{"name":"喆喆生活企業有限公司","id":"94137232","capital":1000000,"representative":"陳_杰","address":"新北市三重區福德北路12號3樓","aliases":[],"relationships":{"upstream":[],"downstream":[]},"webUrl":"https://tbdavid2019.github.io/taiwan-company-network/graph?company=%E5%96%86%E5%96%86%E7%94%9F%E6%B4%BB%E4%BC%81%E6%A5%AD%E6%9C%89%E9%99%90%E5%85%AC%E5%8F%B8"},"喆喆整合行銷有限公司":{"name":"喆喆整合行銷有限公司","id":"94161703","capital":1000000,"representative":"游_珊","address":"花蓮縣新城鄉新城村博愛路18號","aliases":[],"relationships":{"upstream":[],"downstream":[]},"webUrl":"https://tbdavid2019.github.io/taiwan-company-network/graph?company=%E5%96%86%E5%96%86%E6%95%B4%E5%90%88%E8%A1%8C%E9%8A%B7%E6%9C%89%E9%99%90%E5%85%AC%E5%8F%B8"},"喆拓室內裝修設計工程有限公司":{"name":"喆拓室內裝修設計工程有限公司","id":"94267585","capital":500000,"representative":"陳_仁","address":"臺中市北屯區四平路238巷21號地下1樓之5","aliases":[],"relationships":{"upstream":[],"downstream":[]},"webUrl":"https://tbdavid2019.github.io/taiwan-company-network/graph?company=%E5%96%86%E6%8B%93%E5%AE%A4%E5%85%A7%E8%A3%9D%E4%BF%AE%E8%A8%AD%E8%A8%88%E5%B7%A5%E7%A8%8B%E6%9C%89%E9%99%90%E5%85%AC%E5%8F%B8"},"喆琴餐坊有限公司":{"name":"喆琴餐坊有限公司","id":"95460897","capital":100000,"representative":"劉_永","address":"新北市三重區中央北路72號(1樓)","aliases":[],"relationships":{"upstream":[],"downstream":[]},"webUrl":"https://tbdavid2019.github.io/taiwan-company-network/graph?company=%E5%96%86%E7%90%B4%E9%A4%90%E5%9D%8A%E6%9C%89%E9%99%90%E5%85%AC%E5%8F%B8"},"喆元投資股份有限公司":{"name":"喆元投資股份有限公司","id":"95485068","capital":1400000,"representative":"趙_薰","address":"桃園市桃園區青溪里中央街325號","aliases":[],"relationships":{"upstream":[],"downstream":[]},"webUrl":"https://tbdavid2019.github.io/taiwan-company-network/graph?company=%E5%96%86%E5%85%83%E6%8A%95%E8%B3%87%E8%82%A1%E4%BB%BD%E6%9C%89%E9%99%90%E5%85%AC%E5%8F%B8"},"喆騏永續有限公司":{"name":"喆騏永續有限公司","id":"95489727","capital":100000,"representative":"周_泰","address":"臺南市安南區淵東里功安一街266號1樓","aliases":[],"relationships":{"upstream":[],"downstream":[]},"webUrl":"https://tbdavid2019.github.io/taiwan-company-network/graph?company=%E5%96%86%E9%A8%8F%E6%B0%B8%E7%BA%8C%E6%9C%89%E9%99%90%E5%85%AC%E5%8F%B8"},"喆仕有限公司":{"name":"喆仕有限公司","id":"96797482","capital":100000,"representative":"翟_君","address":"花蓮縣花蓮市國強里豐村6號3樓之7","aliases":[],"relationships":{"upstream":[],"downstream":[]},"webUrl":"https://tbdavid2019.github.io/taiwan-company-network/graph?company=%E5%96%86%E4%BB%95%E6%9C%89%E9%99%90%E5%85%AC%E5%8F%B8"},"喆安建設股份有限公司":{"name":"喆安建設股份有限公司","id":"96801492","capital":100000000,"representative":"周_安","address":"新竹縣竹北市光明六路東二段20之3號2樓","aliases":[],"relationships":{"upstream":[],"downstream":[]},"webUrl":"https://tbdavid2019.github.io/taiwan-company-network/graph?company=%E5%96%86%E5%AE%89%E5%BB%BA%E8%A8%AD%E8%82%A1%E4%BB%BD%E6%9C%89%E9%99%90%E5%85%AC%E5%8F%B8"},"喆維環保有限公司":{"name":"喆維環保有限公司","id":"96840256","capital":5000000,"representative":"鍾_強","address":"新北市八里區四維街7號11樓","aliases":[],"relationships":{"upstream":[],"downstream":[]},"webUrl":"https://tbdavid2019.github.io/taiwan-company-network/graph?company=%E5%96%86%E7%B6%AD%E7%92%B0%E4%BF%9D%E6%9C%89%E9%99%90%E5%85%AC%E5%8F%B8"},"喆銓機械有限公司":{"name":"喆銓機械有限公司","id":"97389219","capital":10000000,"representative":"余_鎮","address":"臺中市烏日區前竹里仁義街7號1樓","aliases":[],"relationships":{"upstream":[],"downstream":[]},"webUrl":"https://tbdavid2019.github.io/taiwan-company-network/graph?company=%E5%96%86%E9%8A%93%E6%A9%9F%E6%A2%B0%E6%9C%89%E9%99%90%E5%85%AC%E5%8F%B8"},"喆星工程有限公司":{"name":"喆星工程有限公司","id":"97525930","capital":1000000,"representative":"陳_燕","address":"新竹市北區湳中里湳中街30巷11-1號","aliases":[],"relationships":{"upstream":[],"downstream":[]},"webUrl":"https://tbdavid2019.github.io/taiwan-company-network/graph?company=%E5%96%86%E6%98%9F%E5%B7%A5%E7%A8%8B%E6%9C%89%E9%99%90%E5%85%AC%E5%8F%B8"},"喆禮好宅攻略有限公司":{"name":"喆禮好宅攻略有限公司","id":"133568","capital":3000000,"representative":"趙_君","address":"桃園市中壢區環西路二段201號","aliases":[],"relationships":{"upstream":[],"downstream":[]},"webUrl":"https://tbdavid2019.github.io/taiwan-company-network/graph?company=%E5%96%86%E7%A6%AE%E5%A5%BD%E5%AE%85%E6%94%BB%E7%95%A5%E6%9C%89%E9%99%90%E5%85%AC%E5%8F%B8"},"喆詮投資股份有限公司":{"name":"喆詮投資股份有限公司","id":"230479","capital":2000000,"representative":"余_泓","address":"桃園市觀音區草新里大觀路二段387號","aliases":[],"relationships":{"upstream":[],"downstream":[]},"webUrl":"https://tbdavid2019.github.io/taiwan-company-network/graph?company=%E5%96%86%E8%A9%AE%E6%8A%95%E8%B3%87%E8%82%A1%E4%BB%BD%E6%9C%89%E9%99%90%E5%85%AC%E5%8F%B8"},"喆龍實業有限公司":{"name":"喆龍實業有限公司","id":"4891454","capital":5000000,"representative":"陳_枝","address":"臺北市大安區仁愛路3段24巷11號2樓","aliases":[],"relationships":{"upstream":[],"downstream":[]},"webUrl":"https://tbdavid2019.github.io/taiwan-company-network/graph?company=%E5%96%86%E9%BE%8D%E5%AF%A6%E6%A5%AD%E6%9C%89%E9%99%90%E5%85%AC%E5%8F%B8"},"喆寶有限公司":{"name":"喆寶有限公司","id":"9494428","capital":3000000,"representative":"蔡_鑾","address":"臺北市大安區敦化南路1段376號11樓之1","aliases":[],"relationships":{"upstream":[],"downstream":[]},"webUrl":"https://tbdavid2019.github.io/taiwan-company-network/graph?company=%E5%96%86%E5%AF%B6%E6%9C%89%E9%99%90%E5%85%AC%E5%8F%B8"},"喆嘉國際興業有限公司":{"name":"喆嘉國際興業有限公司","id":"13013555","capital":4000000,"representative":"楊_嘉","address":"臺中市神岡區溝心路33-9號1樓","aliases":[],"relationships":{"upstream":[],"downstream":[]},"webUrl":"https://tbdavid2019.github.io/taiwan-company-network/graph?company=%E5%96%86%E5%98%89%E5%9C%8B%E9%9A%9B%E8%88%88%E6%A5%AD%E6%9C%89%E9%99%90%E5%85%AC%E5%8F%B8"},"喆全股份有限公司":{"name":"喆全股份有限公司","id":"16356337","capital":25000000,"representative":"劉_蓉","address":"臺北市內湖區潭美街558號","aliases":[],"relationships":{"upstream":[],"downstream":["荃揚實業股份有限公司"]},"webUrl":"https://tbdavid2019.github.io/taiwan-company-network/graph?company=%E5%96%86%E5%85%A8%E8%82%A1%E4%BB%BD%E6%9C%89%E9%99%90%E5%85%AC%E5%8F%B8"},"喆翔電子企業有限公司":{"name":"喆翔電子企業有限公司","id":"16689709","capital":2000000,"representative":"蔡_禎","address":"高雄市大寮區中庄里萬隆街2號1樓","aliases":[],"relationships":{"upstream":[],"downstream":[]},"webUrl":"https://tbdavid2019.github.io/taiwan-company-network/graph?company=%E5%96%86%E7%BF%94%E9%9B%BB%E5%AD%90%E4%BC%81%E6%A5%AD%E6%9C%89%E9%99%90%E5%85%AC%E5%8F%B8"},"喆懋天然山水有限公司":{"name":"喆懋天然山水有限公司","id":"16911258","capital":5000000,"representative":"楊_萍","address":"新北市林口區南勢里民族路218號11樓","aliases":[],"relationships":{"upstream":[],"downstream":[]},"webUrl":"https://tbdavid2019.github.io/taiwan-company-network/graph?company=%E5%96%86%E6%87%8B%E5%A4%A9%E7%84%B6%E5%B1%B1%E6%B0%B4%E6%9C%89%E9%99%90%E5%85%AC%E5%8F%B8"},"喆聯股份有限公司":{"name":"喆聯股份有限公司","id":"20850649","capital":29000000,"representative":"干_瑜","address":"臺北市松山區民生東路3段156號7樓之2","aliases":[],"relationships":{"upstream":["英屬維京群島商新紀元建業有限公司","福聯建業國際股份有限公司"],"downstream":[]},"webUrl":"https://tbdavid2019.github.io/taiwan-company-network/graph?company=%E5%96%86%E8%81%AF%E8%82%A1%E4%BB%BD%E6%9C%89%E9%99%90%E5%85%AC%E5%8F%B8"},"喆輝企業有限公司":{"name":"喆輝企業有限公司","id":"23819828","capital":2000000,"representative":"林_枝","address":"彰化縣和美鎮新庄里彰新路二段111巷74號","aliases":[],"relationships":{"upstream":[],"downstream":[]},"webUrl":"https://tbdavid2019.github.io/taiwan-company-network/graph?company=%E5%96%86%E8%BC%9D%E4%BC%81%E6%A5%AD%E6%9C%89%E9%99%90%E5%85%AC%E5%8F%B8"},"喆太企業有限公司":{"name":"喆太企業有限公司","id":"23906007","capital":5000000,"representative":"陳_蓮","address":"臺北市大安區濟南路3段65號6樓","aliases":[],"relationships":{"upstream":[],"downstream":[]},"webUrl":"https://tbdavid2019.github.io/taiwan-company-network/graph?company=%E5%96%86%E5%A4%AA%E4%BC%81%E6%A5%AD%E6%9C%89%E9%99%90%E5%85%AC%E5%8F%B8"},"喆川企業有限公司":{"name":"喆川企業有限公司","id":"23974671","capital":20000000,"representative":"邱_金","address":"臺南市東區裕敬二街76號","aliases":[],"relationships":{"upstream":[],"downstream":[]},"webUrl":"https://tbdavid2019.github.io/taiwan-company-network/graph?company=%E5%96%86%E5%B7%9D%E4%BC%81%E6%A5%AD%E6%9C%89%E9%99%90%E5%85%AC%E5%8F%B8"},"喆園有限公司":{"name":"喆園有限公司","id":"24540317","capital":3000000,"representative":"李_廷","address":"新北市三重區仁華街118巷57號11樓","aliases":[],"relationships":{"upstream":[],"downstream":[]},"webUrl":"https://tbdavid2019.github.io/taiwan-company-network/graph?company=%E5%96%86%E5%9C%92%E6%9C%89%E9%99%90%E5%85%AC%E5%8F%B8"},"喆揚農技股份有限公司":{"name":"喆揚農技股份有限公司","id":"24546635","capital":10000000,"representative":"林_寬","address":"臺北市南港區經貿一路170號11樓之6","aliases":[],"relationships":{"upstream":["神揚建設股份有限公司"],"downstream":[]},"webUrl":"https://tbdavid2019.github.io/taiwan-company-network/graph?company=%E5%96%86%E6%8F%9A%E8%BE%B2%E6%8A%80%E8%82%A1%E4%BB%BD%E6%9C%89%E9%99%90%E5%85%AC%E5%8F%B8"},"喆思智造設計有限公司":{"name":"喆思智造設計有限公司","id":"24549675","capital":1000000,"representative":"葉_珄","address":"臺北市大安區復興南路1段126巷1號5樓之6","aliases":[],"relationships":{"upstream":[],"downstream":[]},"webUrl":"https://tbdavid2019.github.io/taiwan-company-network/graph?company=%E5%96%86%E6%80%9D%E6%99%BA%E9%80%A0%E8%A8%AD%E8%A8%88%E6%9C%89%E9%99%90%E5%85%AC%E5%8F%B8"},"喆立合盈有限公司":{"name":"喆立合盈有限公司","id":"24970603","capital":1000000,"representative":"江_青","address":"臺北市信義區忠孝東路5段1之1號13樓","aliases":[],"relationships":{"upstream":[],"downstream":[]},"webUrl":"https://tbdavid2019.github.io/taiwan-company-network/graph?company=%E5%96%86%E7%AB%8B%E5%90%88%E7%9B%88%E6%9C%89%E9%99%90%E5%85%AC%E5%8F%B8"},"喆詮實業有限公司":{"name":"喆詮實業有限公司","id":"25007310","capital":1500000,"representative":"楊_迎","address":"桃園市龜山區大湖里文三二街66巷23號3樓","aliases":[],"relationships":{"upstream":[],"downstream":[]},"webUrl":"https://tbdavid2019.github.io/taiwan-company-network/graph?company=%E5%96%86%E8%A9%AE%E5%AF%A6%E6%A5%AD%E6%9C%89%E9%99%90%E5%85%AC%E5%8F%B8"},"喆勝工程有限公司":{"name":"喆勝工程有限公司","id":"25064584","capital":5000000,"representative":"王_穎","address":"新北市林口區忠福路137之1號2樓","aliases":[],"relationships":{"upstream":[],"downstream":[]},"webUrl":"https://tbdavid2019.github.io/taiwan-company-network/graph?company=%E5%96%86%E5%8B%9D%E5%B7%A5%E7%A8%8B%E6%9C%89%E9%99%90%E5%85%AC%E5%8F%B8"},"喆文實業股份有限公司":{"name":"喆文實業股份有限公司","id":"27512481","capital":28890000,"representative":"黃_閔","address":"新北市新莊區頭前路167號","aliases":[],"relationships":{"upstream":[],"downstream":[]},"webUrl":"https://tbdavid2019.github.io/taiwan-company-network/graph?company=%E5%96%86%E6%96%87%E5%AF%A6%E6%A5%AD%E8%82%A1%E4%BB%BD%E6%9C%89%E9%99%90%E5%85%AC%E5%8F%B8"},"喆泰機械股份有限公司":{"name":"喆泰機械股份有限公司","id":"27832490","capital":20000000,"representative":"吳_憲","address":"臺中市大里區長榮里西榮路184巷3號2樓","aliases":[],"relationships":{"upstream":[],"downstream":[]},"webUrl":"https://tbdavid2019.github.io/taiwan-company-network/graph?company=%E5%96%86%E6%B3%B0%E6%A9%9F%E6%A2%B0%E8%82%A1%E4%BB%BD%E6%9C%89%E9%99%90%E5%85%AC%E5%8F%B8"},"喆中科技股份有限公司":{"name":"喆中科技股份有限公司","id":"28175000","capital":3000000,"representative":"張_鈺","address":"臺北市內湖區民權東路6段117號2樓之3","aliases":[],"relationships":{"upstream":[],"downstream":[]},"webUrl":"https://tbdavid2019.github.io/taiwan-company-network/graph?company=%E5%96%86%E4%B8%AD%E7%A7%91%E6%8A%80%E8%82%A1%E4%BB%BD%E6%9C%89%E9%99%90%E5%85%AC%E5%8F%B8"},"喆吉影藝製作有限公司":{"name":"喆吉影藝製作有限公司","id":"28228344","capital":3000000,"representative":"陳_偉","address":"臺北市中山區長安東路2段171號11樓之5","aliases":[],"relationships":{"upstream":[],"downstream":[]},"webUrl":"https://tbdavid2019.github.io/taiwan-company-network/graph?company=%E5%96%86%E5%90%89%E5%BD%B1%E8%97%9D%E8%A3%BD%E4%BD%9C%E6%9C%89%E9%99%90%E5%85%AC%E5%8F%B8"},"喆喆品牌形象有限公司":{"name":"喆喆品牌形象有限公司","id":"28467787","capital":3000000,"representative":"江_蓉","address":"臺北市中正區八德路1段5號6樓之2","aliases":[],"relationships":{"upstream":[],"downstream":[]},"webUrl":"https://tbdavid2019.github.io/taiwan-company-network/graph?company=%E5%96%86%E5%96%86%E5%93%81%E7%89%8C%E5%BD%A2%E8%B1%A1%E6%9C%89%E9%99%90%E5%85%AC%E5%8F%B8"},"喆宸投資股份有限公司":{"name":"喆宸投資股份有限公司","id":"28469552","capital":10000000,"representative":"周_菁","address":"臺北市中山區北安路668號1樓","aliases":[],"relationships":{"upstream":[],"downstream":[]},"webUrl":"https://tbdavid2019.github.io/taiwan-company-network/graph?company=%E5%96%86%E5%AE%B8%E6%8A%95%E8%B3%87%E8%82%A1%E4%BB%BD%E6%9C%89%E9%99%90%E5%85%AC%E5%8F%B8"},"喆利有限公司":{"name":"喆利有限公司","id":"28611565","capital":2000000,"representative":"王_禎","address":"臺北市文山區景福街26號1樓  ","aliases":[],"relationships":{"upstream":[],"downstream":[]},"webUrl":"https://tbdavid2019.github.io/taiwan-company-network/graph?company=%E5%96%86%E5%88%A9%E6%9C%89%E9%99%90%E5%85%AC%E5%8F%B8"},"喆達國際股份有限公司":{"name":"喆達國際股份有限公司","id":"28689351","capital":10000000,"representative":"陳_石","address":"臺北市大安區新生南路3段2號7樓之2","aliases":[],"relationships":{"upstream":[],"downstream":[]},"webUrl":"https://tbdavid2019.github.io/taiwan-company-network/graph?company=%E5%96%86%E9%81%94%E5%9C%8B%E9%9A%9B%E8%82%A1%E4%BB%BD%E6%9C%89%E9%99%90%E5%85%AC%E5%8F%B8"},"喆爾鉅企業有限公司":{"name":"喆爾鉅企業有限公司","id":"28740940","capital":5000000,"representative":"蘇_秦","address":"臺中市南屯區大業路561號12樓","aliases":[],"relationships":{"upstream":[],"downstream":[]},"webUrl":"https://tbdavid2019.github.io/taiwan-company-network/graph?company=%E5%96%86%E7%88%BE%E9%89%85%E4%BC%81%E6%A5%AD%E6%9C%89%E9%99%90%E5%85%AC%E5%8F%B8"},"喆士交通有限公司":{"name":"喆士交通有限公司","id":"34245095","capital":3000000,"representative":"洪_英","address":"新北市淡水區英專路21巷12之1號2樓","aliases":[],"relationships":{"upstream":[],"downstream":[]},"webUrl":"https://tbdavid2019.github.io/taiwan-company-network/graph?company=%E5%96%86%E5%A3%AB%E4%BA%A4%E9%80%9A%E6%9C%89%E9%99%90%E5%85%AC%E5%8F%B8"},"喆升有限公司":{"name":"喆升有限公司","id":"42610686","capital":1500000,"representative":"吳_德","address":"臺北市文山區羅斯福路5段236巷3弄32號1樓","aliases":[],"relationships":{"upstream":[],"downstream":[]},"webUrl":"https://tbdavid2019.github.io/taiwan-company-network/graph?company=%E5%96%86%E5%8D%87%E6%9C%89%E9%99%90%E5%85%AC%E5%8F%B8"},"喆亞汽車有限公司":{"name":"喆亞汽車有限公司","id":"42760410","capital":1000000,"representative":"余_儒","address":"宜蘭縣宜蘭市小東里新興路11號","aliases":[],"relationships":{"upstream":[],"downstream":[]},"webUrl":"https://tbdavid2019.github.io/taiwan-company-network/graph?company=%E5%96%86%E4%BA%9E%E6%B1%BD%E8%BB%8A%E6%9C%89%E9%99%90%E5%85%AC%E5%8F%B8"},"喆美文創有限公司":{"name":"喆美文創有限公司","id":"42831169","capital":2800000,"representative":"王_馨","address":"臺北市中山區合江街116巷28號1樓","aliases":[],"relationships":{"upstream":[],"downstream":[]},"webUrl":"https://tbdavid2019.github.io/taiwan-company-network/graph?company=%E5%96%86%E7%BE%8E%E6%96%87%E5%89%B5%E6%9C%89%E9%99%90%E5%85%AC%E5%8F%B8"},"喆方資產管理股份有限公司":{"name":"喆方資產管理股份有限公司","id":"42899809","capital":1000000,"representative":"賴_維","address":"臺中市西屯區漢口路二段136之5號5樓","aliases":[],"relationships":{"upstream":[],"downstream":[]},"webUrl":"https://tbdavid2019.github.io/taiwan-company-network/graph?company=%E5%96%86%E6%96%B9%E8%B3%87%E7%94%A2%E7%AE%A1%E7%90%86%E8%82%A1%E4%BB%BD%E6%9C%89%E9%99%90%E5%85%AC%E5%8F%B8"},"喆寓室內裝修設計有限公司":{"name":"喆寓室內裝修設計有限公司","id":"42924862","capital":3500000,"representative":"陳_齊","address":"臺南市安平區郡平路248號","aliases":[],"relationships":{"upstream":[],"downstream":[]},"webUrl":"https://tbdavid2019.github.io/taiwan-company-network/graph?company=%E5%96%86%E5%AF%93%E5%AE%A4%E5%85%A7%E8%A3%9D%E4%BF%AE%E8%A8%AD%E8%A8%88%E6%9C%89%E9%99%90%E5%85%AC%E5%8F%B8"},"喆好有限公司":{"name":"喆好有限公司","id":"43425506","capital":2300000,"representative":"許_芸","address":"臺北市大安區瑞安街198號1樓","aliases":[],"relationships":{"upstream":[],"downstream":[]},"webUrl":"https://tbdavid2019.github.io/taiwan-company-network/graph?company=%E5%96%86%E5%A5%BD%E6%9C%89%E9%99%90%E5%85%AC%E5%8F%B8"},"喆認國際有限公司":{"name":"喆認國際有限公司","id":"45098154","capital":5000000,"representative":"趙_君","address":"桃園市桃園區大興西路一段35號（2樓）","aliases":[],"relationships":{"upstream":[],"downstream":[]},"webUrl":"https://tbdavid2019.github.io/taiwan-company-network/graph?company=%E5%96%86%E8%AA%8D%E5%9C%8B%E9%9A%9B%E6%9C%89%E9%99%90%E5%85%AC%E5%8F%B8"},"喆馨企業有限公司":{"name":"喆馨企業有限公司","id":"50758943","capital":1000000,"representative":"陳_吉","address":"臺北市中山區北安路835號  ","aliases":[],"relationships":{"upstream":[],"downstream":[]},"webUrl":"https://tbdavid2019.github.io/taiwan-company-network/graph?company=%E5%96%86%E9%A6%A8%E4%BC%81%E6%A5%AD%E6%9C%89%E9%99%90%E5%85%AC%E5%8F%B8"},"喆園事業股份有限公司":{"name":"喆園事業股份有限公司","id":"53102104","capital":17850000,"representative":"陳_錩","address":"臺北市中山區建國北路1段80號1樓及2樓","aliases":[],"relationships":{"upstream":[],"downstream":[]},"webUrl":"https://tbdavid2019.github.io/taiwan-company-network/graph?company=%E5%96%86%E5%9C%92%E4%BA%8B%E6%A5%AD%E8%82%A1%E4%BB%BD%E6%9C%89%E9%99%90%E5%85%AC%E5%8F%B8"},"喆學影像製作有限公司":{"name":"喆學影像製作有限公司","id":"53197072","capital":1200000,"representative":"楊_喆","address":"新北市中和區華新街143巷67弄9號","aliases":[],"relationships":{"upstream":[],"downstream":[]},"webUrl":"https://tbdavid2019.github.io/taiwan-company-network/graph?company=%E5%96%86%E5%AD%B8%E5%BD%B1%E5%83%8F%E8%A3%BD%E4%BD%9C%E6%9C%89%E9%99%90%E5%85%AC%E5%8F%B8"},"喆喆水產有限公司":{"name":"喆喆水產有限公司","id":"53369314","capital":2000000,"representative":"陳_霖","address":"臺北市中山區長安東路1段16號8樓之3","aliases":[],"relationships":{"upstream":[],"downstream":[]},"webUrl":"https://tbdavid2019.github.io/taiwan-company-network/graph?company=%E5%96%86%E5%96%86%E6%B0%B4%E7%94%A2%E6%9C%89%E9%99%90%E5%85%AC%E5%8F%B8"},"喆崧有限公司":{"name":"喆崧有限公司","id":"53606386","capital":500000,"representative":"何_樺","address":"臺南市永康區東橋里大橋一街324巷117弄9號1樓","aliases":[],"relationships":{"upstream":[],"downstream":[]},"webUrl":"https://tbdavid2019.github.io/taiwan-company-network/graph?company=%E5%96%86%E5%B4%A7%E6%9C%89%E9%99%90%E5%85%AC%E5%8F%B8"},"喆豐環保科技有限公司":{"name":"喆豐環保科技有限公司","id":"53709101","capital":1000000,"representative":"王_喆","address":"新北市土城區員林街18之1號5樓  ","aliases":[],"relationships":{"upstream":[],"downstream":[]},"webUrl":"https://tbdavid2019.github.io/taiwan-company-network/graph?company=%E5%96%86%E8%B1%90%E7%92%B0%E4%BF%9D%E7%A7%91%E6%8A%80%E6%9C%89%E9%99%90%E5%85%AC%E5%8F%B8"},"喆翔國際有限公司":{"name":"喆翔國際有限公司","id":"53918156","capital":1000000,"representative":"何_圳","address":"臺北市松山區南京東路5段316號8樓之8","aliases":[],"relationships":{"upstream":[],"downstream":[]},"webUrl":"https://tbdavid2019.github.io/taiwan-company-network/graph?company=%E5%96%86%E7%BF%94%E5%9C%8B%E9%9A%9B%E6%9C%89%E9%99%90%E5%85%AC%E5%8F%B8"},"喆方室內裝修設計工程有限公司":{"name":"喆方室內裝修設計工程有限公司","id":"53943401","capital":100000000,"representative":"李_琇","address":"臺北市松山區敦化北路207號6樓","aliases":[],"relationships":{"upstream":[],"downstream":[]},"webUrl":"https://tbdavid2019.github.io/taiwan-company-network/graph?company=%E5%96%86%E6%96%B9%E5%AE%A4%E5%85%A7%E8%A3%9D%E4%BF%AE%E8%A8%AD%E8%A8%88%E5%B7%A5%E7%A8%8B%E6%9C%89%E9%99%90%E5%85%AC%E5%8F%B8"},"喆洋營造有限公司":{"name":"喆洋營造有限公司","id":"53966797","capital":3000000,"representative":"劉_淋","address":"嘉義市西區磚磘里玉山路220號3樓","aliases":[],"relationships":{"upstream":[],"downstream":[]},"webUrl":"https://tbdavid2019.github.io/taiwan-company-network/graph?company=%E5%96%86%E6%B4%8B%E7%87%9F%E9%80%A0%E6%9C%89%E9%99%90%E5%85%AC%E5%8F%B8"},"喆喬工程有限公司":{"name":"喆喬工程有限公司","id":"54200119","capital":3000000,"representative":"林_鴻","address":"高雄市小港區鳳林路53號1樓","aliases":[],"relationships":{"upstream":[],"downstream":[]},"webUrl":"https://tbdavid2019.github.io/taiwan-company-network/graph?company=%E5%96%86%E5%96%AC%E5%B7%A5%E7%A8%8B%E6%9C%89%E9%99%90%E5%85%AC%E5%8F%B8"},"喆勝興業有限公司":{"name":"喆勝興業有限公司","id":"54965368","capital":200000,"representative":"劉_哲","address":"新北市三重區仁愛街43巷83號（1樓）","aliases":[],"relationships":{"upstream":[],"downstream":[]},"webUrl":"https://tbdavid2019.github.io/taiwan-company-network/graph?company=%E5%96%86%E5%8B%9D%E8%88%88%E6%A5%AD%E6%9C%89%E9%99%90%E5%85%AC%E5%8F%B8"},"喆園投資有限公司":{"name":"喆園投資有限公司","id":"54988334","capital":12000000,"representative":"楊_清","address":"新竹縣湖口鄉達生七街33號1樓","aliases":[],"relationships":{"upstream":[],"downstream":[]},"webUrl":"https://tbdavid2019.github.io/taiwan-company-network/graph?company=%E5%96%86%E5%9C%92%E6%8A%95%E8%B3%87%E6%9C%89%E9%99%90%E5%85%AC%E5%8F%B8"},"喆睿有限公司":{"name":"喆睿有限公司","id":"60333576","capital":250000,"representative":"李_財","address":"新北市新莊區富貴路492號6樓","aliases":[],"relationships":{"upstream":[],"downstream":[]},"webUrl":"https://tbdavid2019.github.io/taiwan-company-network/graph?company=%E5%96%86%E7%9D%BF%E6%9C%89%E9%99%90%E5%85%AC%E5%8F%B8"},"喆安機電有限公司":{"name":"喆安機電有限公司","id":"60480020","capital":500000,"representative":"何_誌","address":"高雄市燕巢區燕南二街61號2樓","aliases":[],"relationships":{"upstream":[],"downstream":[]},"webUrl":"https://tbdavid2019.github.io/taiwan-company-network/graph?company=%E5%96%86%E5%AE%89%E6%A9%9F%E9%9B%BB%E6%9C%89%E9%99%90%E5%85%AC%E5%8F%B8"},"喆喆環保顧問有限公司":{"name":"喆喆環保顧問有限公司","id":"60516511","capital":3000000,"representative":"賴_豪","address":"嘉義縣民雄鄉東榮村文化路24-7號二樓","aliases":[],"relationships":{"upstream":[],"downstream":[]},"webUrl":"https://tbdavid2019.github.io/taiwan-company-network/graph?company=%E5%96%86%E5%96%86%E7%92%B0%E4%BF%9D%E9%A1%A7%E5%95%8F%E6%9C%89%E9%99%90%E5%85%AC%E5%8F%B8"},"喆理投資股份有限公司":{"name":"喆理投資股份有限公司","id":"60583399","capital":1000000,"representative":"林_麒","address":"臺北市大安區復興南路1段137號12樓之5","aliases":[],"relationships":{"upstream":[],"downstream":[]},"webUrl":"https://tbdavid2019.github.io/taiwan-company-network/graph?company=%E5%96%86%E7%90%86%E6%8A%95%E8%B3%87%E8%82%A1%E4%BB%BD%E6%9C%89%E9%99%90%E5%85%AC%E5%8F%B8"},"喆君投資有限公司":{"name":"喆君投資有限公司","id":"60645450","capital":15236632,"representative":"廖_志","address":"臺北市中山區南京東路2段172號6樓","aliases":[],"relationships":{"upstream":[],"downstream":[]},"webUrl":"https://tbdavid2019.github.io/taiwan-company-network/graph?company=%E5%96%86%E5%90%9B%E6%8A%95%E8%B3%87%E6%9C%89%E9%99%90%E5%85%AC%E5%8F%B8"},"喆賀有限公司":{"name":"喆賀有限公司","id":"60665758","capital":500000,"representative":"黃_軒","address":"臺南市北區海安路3段800號5樓之2","aliases":[],"relationships":{"upstream":[],"downstream":[]},"webUrl":"https://tbdavid2019.github.io/taiwan-company-network/graph?company=%E5%96%86%E8%B3%80%E6%9C%89%E9%99%90%E5%85%AC%E5%8F%B8"},"喆鑫有限公司":{"name":"喆鑫有限公司","id":"62136371","capital":1000000,"representative":"周_鑫","address":"臺中市大里區立仁里好來六街六巷1號2樓  ","aliases":[],"relationships":{"upstream":[],"downstream":[]},"webUrl":"https://tbdavid2019.github.io/taiwan-company-network/graph?company=%E5%96%86%E9%91%AB%E6%9C%89%E9%99%90%E5%85%AC%E5%8F%B8"},"喆川室內設計有限公司":{"name":"喆川室內設計有限公司","id":"67025705","capital":1000000,"representative":"張_喬","address":"新北市中和區中和路217巷8之1號","aliases":[],"relationships":{"upstream":[],"downstream":[]},"webUrl":"https://tbdavid2019.github.io/taiwan-company-network/graph?company=%E5%96%86%E5%B7%9D%E5%AE%A4%E5%85%A7%E8%A8%AD%E8%A8%88%E6%9C%89%E9%99%90%E5%85%AC%E5%8F%B8"},"喆新實業有限公司":{"name":"喆新實業有限公司","id":"80115399","capital":1000000,"representative":"盧_煒","address":"高雄市鳳山區文澄街32號15樓","aliases":[],"relationships":{"upstream":[],"downstream":[]},"webUrl":"https://tbdavid2019.github.io/taiwan-company-network/graph?company=%E5%96%86%E6%96%B0%E5%AF%A6%E6%A5%AD%E6%9C%89%E9%99%90%E5%85%AC%E5%8F%B8"},"喆泉建設有限公司":{"name":"喆泉建設有限公司","id":"80376751","capital":5000000,"representative":"蔡_智","address":"高雄市鼓山區裕誠路1612號","aliases":[],"relationships":{"upstream":[],"downstream":[]},"webUrl":"https://tbdavid2019.github.io/taiwan-company-network/graph?company=%E5%96%86%E6%B3%89%E5%BB%BA%E8%A8%AD%E6%9C%89%E9%99%90%E5%85%AC%E5%8F%B8"},"喆洋食品原料有限公司":{"name":"喆洋食品原料有限公司","id":"80467767","capital":1000000,"representative":"洪_騏","address":"雲林縣斗南鎮新光里北辰路13號  ","aliases":[],"relationships":{"upstream":[],"downstream":[]},"webUrl":"https://tbdavid2019.github.io/taiwan-company-network/graph?company=%E5%96%86%E6%B4%8B%E9%A3%9F%E5%93%81%E5%8E%9F%E6%96%99%E6%9C%89%E9%99%90%E5%85%AC%E5%8F%B8"},"喆祥工程有限公司":{"name":"喆祥工程有限公司","id":"80643075","capital":1000000,"representative":"張_誌","address":"高雄市楠梓區德中路40巷4號1樓","aliases":[],"relationships":{"upstream":[],"downstream":[]},"webUrl":"https://tbdavid2019.github.io/taiwan-company-network/graph?company=%E5%96%86%E7%A5%A5%E5%B7%A5%E7%A8%8B%E6%9C%89%E9%99%90%E5%85%AC%E5%8F%B8"},"喆禾室內裝修工程有限公司":{"name":"喆禾室內裝修工程有限公司","id":"82845225","capital":3000000,"representative":"張_嘉","address":"臺北市中山區雙城街46巷11之2號1樓","aliases":[],"relationships":{"upstream":[],"downstream":[]},"webUrl":"https://tbdavid2019.github.io/taiwan-company-network/graph?company=%E5%96%86%E7%A6%BE%E5%AE%A4%E5%85%A7%E8%A3%9D%E4%BF%AE%E5%B7%A5%E7%A8%8B%E6%9C%89%E9%99%90%E5%85%AC%E5%8F%B8"},"喆元興業有限公司":{"name":"喆元興業有限公司","id":"82877128","capital":700000,"representative":"王_勝","address":"臺北市中山區建國北路3段145號","aliases":[],"relationships":{"upstream":[],"downstream":[]},"webUrl":"https://tbdavid2019.github.io/taiwan-company-network/graph?company=%E5%96%86%E5%85%83%E8%88%88%E6%A5%AD%E6%9C%89%E9%99%90%E5%85%AC%E5%8F%B8"},"喆韻開發有限公司":{"name":"喆韻開發有限公司","id":"83070608","capital":1000000,"representative":"蔣_芃","address":"臺中市南屯區南屯里五權西路二段666號6樓之4","aliases":[],"relationships":{"upstream":[],"downstream":[]},"webUrl":"https://tbdavid2019.github.io/taiwan-company-network/graph?company=%E5%96%86%E9%9F%BB%E9%96%8B%E7%99%BC%E6%9C%89%E9%99%90%E5%85%AC%E5%8F%B8"},"喆天有限公司":{"name":"喆天有限公司","id":"83099871","capital":500000,"representative":"王_偉","address":"新北市板橋區合宜路121號（1樓）","aliases":[],"relationships":{"upstream":[],"downstream":[]},"webUrl":"https://tbdavid2019.github.io/taiwan-company-network/graph?company=%E5%96%86%E5%A4%A9%E6%9C%89%E9%99%90%E5%85%AC%E5%8F%B8"},"喆宇實業有限公司":{"name":"喆宇實業有限公司","id":"83109097","capital":100000,"representative":"謝_安","address":"新北市中和區中山路3段39號17樓之5","aliases":[],"relationships":{"upstream":[],"downstream":[]},"webUrl":"https://tbdavid2019.github.io/taiwan-company-network/graph?company=%E5%96%86%E5%AE%87%E5%AF%A6%E6%A5%AD%E6%9C%89%E9%99%90%E5%85%AC%E5%8F%B8"},"喆運有限公司":{"name":"喆運有限公司","id":"83130373","capital":6200000,"representative":"李_欣","address":"臺中市北屯區文心路四段83號14樓","aliases":[],"relationships":{"upstream":[],"downstream":[]},"webUrl":"https://tbdavid2019.github.io/taiwan-company-network/graph?company=%E5%96%86%E9%81%8B%E6%9C%89%E9%99%90%E5%85%AC%E5%8F%B8"},"喆旭有限公司":{"name":"喆旭有限公司","id":"83191547","capital":1500000,"representative":"吳_浚","address":"臺北市萬華區富民路81號4樓","aliases":[],"relationships":{"upstream":[],"downstream":[]},"webUrl":"https://tbdavid2019.github.io/taiwan-company-network/graph?company=%E5%96%86%E6%97%AD%E6%9C%89%E9%99%90%E5%85%AC%E5%8F%B8"},"喆昌多媒體股份有限公司":{"name":"喆昌多媒體股份有限公司","id":"83266151","capital":50100000,"representative":"陳_政","address":"新北市林口區文化三路2段356號3樓","aliases":[],"relationships":{"upstream":[],"downstream":["成基齒輪股份有限公司"]},"webUrl":"https://tbdavid2019.github.io/taiwan-company-network/graph?company=%E5%96%86%E6%98%8C%E5%A4%9A%E5%AA%92%E9%AB%94%E8%82%A1%E4%BB%BD%E6%9C%89%E9%99%90%E5%85%AC%E5%8F%B8"},"喆利國際股份有限公司":{"name":"喆利國際股份有限公司","id":"83307370","capital":17450000,"representative":"李_吉","address":"新北市新店區中興路2段218巷11號7樓","aliases":[],"relationships":{"upstream":[],"downstream":[]},"webUrl":"https://tbdavid2019.github.io/taiwan-company-network/graph?company=%E5%96%86%E5%88%A9%E5%9C%8B%E9%9A%9B%E8%82%A1%E4%BB%BD%E6%9C%89%E9%99%90%E5%85%AC%E5%8F%B8"},"喆翔有限公司":{"name":"喆翔有限公司","id":"83402557","capital":1000000,"representative":"黃_蓉","address":"桃園市桃園區東山里15鄰春日路83號10樓","aliases":[],"relationships":{"upstream":[],"downstream":["理想生活服務股份有限公司"]},"webUrl":"https://tbdavid2019.github.io/taiwan-company-network/graph?company=%E5%96%86%E7%BF%94%E6%9C%89%E9%99%90%E5%85%AC%E5%8F%B8"},"喆友建設股份有限公司":{"name":"喆友建設股份有限公司","id":"83454533","capital":200000000,"representative":"郭_興","address":"新北市永和區保生路1號4樓之1","aliases":[],"relationships":{"upstream":[],"downstream":[]},"webUrl":"https://tbdavid2019.github.io/taiwan-company-network/graph?company=%E5%96%86%E5%8F%8B%E5%BB%BA%E8%A8%AD%E8%82%A1%E4%BB%BD%E6%9C%89%E9%99%90%E5%85%AC%E5%8F%B8"},"喆亮國際股份有限公司":{"name":"喆亮國際股份有限公司","id":"83476662","capital":5300000,"representative":"陳_治","address":"臺北市信義區基隆路2段189號17樓","aliases":[],"relationships":{"upstream":[],"downstream":[]},"webUrl":"https://tbdavid2019.github.io/taiwan-company-network/graph?company=%E5%96%86%E4%BA%AE%E5%9C%8B%E9%9A%9B%E8%82%A1%E4%BB%BD%E6%9C%89%E9%99%90%E5%85%AC%E5%8F%B8"},"喆安成實業有限公司":{"name":"喆安成實業有限公司","id":"84763425","capital":5000000,"representative":"童_邦","address":"臺北市中山區長安東路2段110號3樓  ","aliases":[],"relationships":{"upstream":[],"downstream":[]},"webUrl":"https://tbdavid2019.github.io/taiwan-company-network/graph?company=%E5%96%86%E5%AE%89%E6%88%90%E5%AF%A6%E6%A5%AD%E6%9C%89%E9%99%90%E5%85%AC%E5%8F%B8"},"喆昶工程股份有限公司":{"name":"喆昶工程股份有限公司","id":"86142128","capital":5000000,"representative":"曾_健","address":"臺北市信義區松信路139號","aliases":[],"relationships":{"upstream":[],"downstream":[]},"webUrl":"https://tbdavid2019.github.io/taiwan-company-network/graph?company=%E5%96%86%E6%98%B6%E5%B7%A5%E7%A8%8B%E8%82%A1%E4%BB%BD%E6%9C%89%E9%99%90%E5%85%AC%E5%8F%B8"},"喆暘室內裝修設計有限公司":{"name":"喆暘室內裝修設計有限公司","id":"86166444","capital":1000000,"representative":"劉_森","address":"臺北市大安區通安街168號","aliases":[],"relationships":{"upstream":[],"downstream":[]},"webUrl":"https://tbdavid2019.github.io/taiwan-company-network/graph?company=%E5%96%86%E6%9A%98%E5%AE%A4%E5%85%A7%E8%A3%9D%E4%BF%AE%E8%A8%AD%E8%A8%88%E6%9C%89%E9%99%90%E5%85%AC%E5%8F%B8"},"喆冠電子企業有限公司":{"name":"喆冠電子企業有限公司","id":"86302975","capital":10000000,"representative":"呂_揚","address":"臺北市中山區南京東路1段92號11樓之2","aliases":[],"relationships":{"upstream":[],"downstream":[]},"webUrl":"https://tbdavid2019.github.io/taiwan-company-network/graph?company=%E5%96%86%E5%86%A0%E9%9B%BB%E5%AD%90%E4%BC%81%E6%A5%AD%E6%9C%89%E9%99%90%E5%85%AC%E5%8F%B8"},"喆昕有限公司":{"name":"喆昕有限公司","id":"89151374","capital":88000,"representative":"林_蕙","address":"屏東縣麟洛鄉田道村中華路270號","aliases":[],"relationships":{"upstream":[],"downstream":[]},"webUrl":"https://tbdavid2019.github.io/taiwan-company-network/graph?company=%E5%96%86%E6%98%95%E6%9C%89%E9%99%90%E5%85%AC%E5%8F%B8"},"喆立合興有限公司":{"name":"喆立合興有限公司","id":"89194916","capital":1000000,"representative":"李_仁","address":"新北市板橋區雨農路50號26樓","aliases":[],"relationships":{"upstream":[],"downstream":[]},"webUrl":"https://tbdavid2019.github.io/taiwan-company-network/graph?company=%E5%96%86%E7%AB%8B%E5%90%88%E8%88%88%E6%9C%89%E9%99%90%E5%85%AC%E5%8F%B8"},"喆第實業股份有限公司":{"name":"喆第實業股份有限公司","id":"89475042","capital":10000000,"representative":"秦_蘭","address":"臺北市中正區杭州南路1段71巷3之1號","aliases":[],"relationships":{"upstream":[],"downstream":[]},"webUrl":"https://tbdavid2019.github.io/taiwan-company-network/graph?company=%E5%96%86%E7%AC%AC%E5%AF%A6%E6%A5%AD%E8%82%A1%E4%BB%BD%E6%9C%89%E9%99%90%E5%85%AC%E5%8F%B8"},"喆夏有限公司":{"name":"喆夏有限公司","id":"90028346","capital":100000,"representative":"王_絜","address":"新北市新店區中正路700巷74號16樓","aliases":[],"relationships":{"upstream":[],"downstream":[]},"webUrl":"https://tbdavid2019.github.io/taiwan-company-network/graph?company=%E5%96%86%E5%A4%8F%E6%9C%89%E9%99%90%E5%85%AC%E5%8F%B8"},"喆城開發股份有限公司":{"name":"喆城開發股份有限公司","id":"90281163","capital":1400000,"representative":"戴_芝","address":"臺中市西屯區協和里安和路33之5號1樓","aliases":[],"relationships":{"upstream":[],"downstream":[]},"webUrl":"https://tbdavid2019.github.io/taiwan-company-network/graph?company=%E5%96%86%E5%9F%8E%E9%96%8B%E7%99%BC%E8%82%A1%E4%BB%BD%E6%9C%89%E9%99%90%E5%85%AC%E5%8F%B8"},"喆昊科技股份有限公司":{"name":"喆昊科技股份有限公司","id":"90346736","capital":200000000,"representative":"梁_成","address":"新竹市東區光復路一段472號6樓之8","aliases":[],"relationships":{"upstream":["喆富創新科技股份有限公司","喆鑫投資有限公司"],"downstream":[]},"webUrl":"https://tbdavid2019.github.io/taiwan-company-network/graph?company=%E5%96%86%E6%98%8A%E7%A7%91%E6%8A%80%E8%82%A1%E4%BB%BD%E6%9C%89%E9%99%90%E5%85%AC%E5%8F%B8"},"喆語有限公司":{"name":"喆語有限公司","id":"90367345","capital":100000,"representative":"楊_嵐","address":"臺北市中山區建國北路1段33巷5號1樓","aliases":[],"relationships":{"upstream":[],"downstream":[]},"webUrl":"https://tbdavid2019.github.io/taiwan-company-network/graph?company=%E5%96%86%E8%AA%9E%E6%9C%89%E9%99%90%E5%85%AC%E5%8F%B8"},"喆楷國際貿易有限公司":{"name":"喆楷國際貿易有限公司","id":"90463939","capital":1000000,"representative":"李_婷","address":"新北市新店區寶橋路235巷127號4樓之1","aliases":[],"relationships":{"upstream":[],"downstream":[]},"webUrl":"https://tbdavid2019.github.io/taiwan-company-network/graph?company=%E5%96%86%E6%A5%B7%E5%9C%8B%E9%9A%9B%E8%B2%BF%E6%98%93%E6%9C%89%E9%99%90%E5%85%AC%E5%8F%B8"},"喆喆能源工程有限公司":{"name":"喆喆能源工程有限公司","id":"90471591","capital":2000000,"representative":"楊_吉","address":"高雄市三民區鼎富路52號","aliases":[],"relationships":{"upstream":[],"downstream":[]},"webUrl":"https://tbdavid2019.github.io/taiwan-company-network/graph?company=%E5%96%86%E5%96%86%E8%83%BD%E6%BA%90%E5%B7%A5%E7%A8%8B%E6%9C%89%E9%99%90%E5%85%AC%E5%8F%B8"},"喆英企業有限公司":{"name":"喆英企業有限公司","id":"90860682","capital":12000000,"representative":"邱_宏","address":"屏東縣屏東市大連里建豐路2巷49號10樓","aliases":[],"relationships":{"upstream":[],"downstream":[]},"webUrl":"https://tbdavid2019.github.io/taiwan-company-network/graph?company=%E5%96%86%E8%8B%B1%E4%BC%81%E6%A5%AD%E6%9C%89%E9%99%90%E5%85%AC%E5%8F%B8"},"喆楷實業有限公司":{"name":"喆楷實業有限公司","id":"91028631","capital":100000,"representative":"王_智","address":"桃園市楊梅區四維里益新三街3號4樓之1","aliases":[],"relationships":{"upstream":[],"downstream":[]},"webUrl":"https://tbdavid2019.github.io/taiwan-company-network/graph?company=%E5%96%86%E6%A5%B7%E5%AF%A6%E6%A5%AD%E6%9C%89%E9%99%90%E5%85%AC%E5%8F%B8"},"喆詠股份有限公司":{"name":"喆詠股份有限公司","id":"91087856","capital":5000000,"representative":"李_恩","address":"新北市板橋區華江一路628號","aliases":[],"relationships":{"upstream":[],"downstream":[]},"webUrl":"https://tbdavid2019.github.io/taiwan-company-network/graph?company=%E5%96%86%E8%A9%A0%E8%82%A1%E4%BB%BD%E6%9C%89%E9%99%90%E5%85%AC%E5%8F%B8"},"喆優金屬有限公司":{"name":"喆優金屬有限公司","id":"93378824","capital":5000000,"representative":"曾_吉","address":"新北市土城區延吉街253巷18弄3號5樓","aliases":[],"relationships":{"upstream":[],"downstream":[]},"webUrl":"https://tbdavid2019.github.io/taiwan-company-network/graph?company=%E5%96%86%E5%84%AA%E9%87%91%E5%B1%AC%E6%9C%89%E9%99%90%E5%85%AC%E5%8F%B8"},"喆彩印刷整合有限公司":{"name":"喆彩印刷整合有限公司","id":"93381004","capital":100000,"representative":"史_豪","address":"新北市新店區中華路48巷20號2樓","aliases":[],"relationships":{"upstream":[],"downstream":[]},"webUrl":"https://tbdavid2019.github.io/taiwan-company-network/graph?company=%E5%96%86%E5%BD%A9%E5%8D%B0%E5%88%B7%E6%95%B4%E5%90%88%E6%9C%89%E9%99%90%E5%85%AC%E5%8F%B8"},"喆蟄管理顧問有限公司":{"name":"喆蟄管理顧問有限公司","id":"93526374","capital":100000,"representative":"陳_吉","address":"新北市中和區景新街345號3樓之1","aliases":[],"relationships":{"upstream":[],"downstream":[]},"webUrl":"https://tbdavid2019.github.io/taiwan-company-network/graph?company=%E5%96%86%E8%9F%84%E7%AE%A1%E7%90%86%E9%A1%A7%E5%95%8F%E6%9C%89%E9%99%90%E5%85%AC%E5%8F%B8"},"喆晨投資有限公司":{"name":"喆晨投資有限公司","id":"93546456","capital":4600000,"representative":"林_瑋","address":"臺北市中正區重慶南路1段57號9樓之3","aliases":[],"relationships":{"upstream":[],"downstream":[]},"webUrl":"https://tbdavid2019.github.io/taiwan-company-network/graph?company=%E5%96%86%E6%99%A8%E6%8A%95%E8%B3%87%E6%9C%89%E9%99%90%E5%85%AC%E5%8F%B8"},"喆安文化藝術有限公司":{"name":"喆安文化藝術有限公司","id":"93570201","capital":1000000,"representative":"楊_宜","address":"新北市深坑區北深路3段270巷16號6樓之6","aliases":[],"relationships":{"upstream":[],"downstream":[]},"webUrl":"https://tbdavid2019.github.io/taiwan-company-network/graph?company=%E5%96%86%E5%AE%89%E6%96%87%E5%8C%96%E8%97%9D%E8%A1%93%E6%9C%89%E9%99%90%E5%85%AC%E5%8F%B8"},"喆禮資產開發有限公司":{"name":"喆禮資產開發有限公司","id":"93695949","capital":1000000,"representative":"趙_君","address":"桃園市桃園區青溪里中央街321號","aliases":[],"relationships":{"upstream":[],"downstream":[]},"webUrl":"https://tbdavid2019.github.io/taiwan-company-network/graph?company=%E5%96%86%E7%A6%AE%E8%B3%87%E7%94%A2%E9%96%8B%E7%99%BC%E6%9C%89%E9%99%90%E5%85%AC%E5%8F%B8"},"喆維國際貿易有限公司":{"name":"喆維國際貿易有限公司","id":"94000518","capital":4000000,"representative":"康_維","address":"新北市汐止區東勢街190巷11號2樓","aliases":[],"relationships":{"upstream":[],"downstream":[]},"webUrl":"https://tbdavid2019.github.io/taiwan-company-network/graph?company=%E5%96%86%E7%B6%AD%E5%9C%8B%E9%9A%9B%E8%B2%BF%E6%98%93%E6%9C%89%E9%99%90%E5%85%AC%E5%8F%B8"},"喆茶有限公司":{"name":"喆茶有限公司","id":"94124270","capital":1000000,"representative":"徐_漢","address":"高雄市楠梓區後昌路760號1樓","aliases":[],"relationships":{"upstream":[],"downstream":[]},"webUrl":"https://tbdavid2019.github.io/taiwan-company-network/graph?company=%E5%96%86%E8%8C%B6%E6%9C%89%E9%99%90%E5%85%AC%E5%8F%B8"},"喆潤有限公司":{"name":"喆潤有限公司","id":"94153485","capital":500000,"representative":"徐_漢","address":"高雄市左營區重信路598號1樓","aliases":[],"relationships":{"upstream":[],"downstream":[]},"webUrl":"https://tbdavid2019.github.io/taiwan-company-network/graph?company=%E5%96%86%E6%BD%A4%E6%9C%89%E9%99%90%E5%85%AC%E5%8F%B8"},"喆任事業有限公司":{"name":"喆任事業有限公司","id":"94171527","capital":200000,"representative":"宋_庭","address":"桃園市八德區豐田一路23號2樓","aliases":[],"relationships":{"upstream":[],"downstream":[]},"webUrl":"https://tbdavid2019.github.io/taiwan-company-network/graph?company=%E5%96%86%E4%BB%BB%E4%BA%8B%E6%A5%AD%E6%9C%89%E9%99%90%E5%85%AC%E5%8F%B8"},"喆牛有限公司":{"name":"喆牛有限公司","id":"94192142","capital":2000000,"representative":"余_豐","address":"新北市新莊區化成路205號之19四樓","aliases":[],"relationships":{"upstream":[],"downstream":[]},"webUrl":"https://tbdavid2019.github.io/taiwan-company-network/graph?company=%E5%96%86%E7%89%9B%E6%9C%89%E9%99%90%E5%85%AC%E5%8F%B8"},"喆暘電子科技有限公司":{"name":"喆暘電子科技有限公司","id":"94240593","capital":1000000,"representative":"林_超","address":"新北市汐止區建成路142巷19弄7號8樓","aliases":[],"relationships":{"upstream":[],"downstream":[]},"webUrl":"https://tbdavid2019.github.io/taiwan-company-network/graph?company=%E5%96%86%E6%9A%98%E9%9B%BB%E5%AD%90%E7%A7%91%E6%8A%80%E6%9C%89%E9%99%90%E5%85%AC%E5%8F%B8"},"喆高設計實業有限公司":{"name":"喆高設計實業有限公司","id":"94241381","capital":100000,"representative":"高_哲","address":"新北市樹林區文化街29號3樓之3","aliases":[],"relationships":{"upstream":[],"downstream":[]},"webUrl":"https://tbdavid2019.github.io/taiwan-company-network/graph?company=%E5%96%86%E9%AB%98%E8%A8%AD%E8%A8%88%E5%AF%A6%E6%A5%AD%E6%9C%89%E9%99%90%E5%85%AC%E5%8F%B8"},"喆祥綜合工程有限公司":{"name":"喆祥綜合工程有限公司","id":"95445550","capital":100000,"representative":"張_哲","address":"嘉義縣水上鄉龍德村十一指厝8-87號","aliases":[],"relationships":{"upstream":[],"downstream":[]},"webUrl":"https://tbdavid2019.github.io/taiwan-company-network/graph?company=%E5%96%86%E7%A5%A5%E7%B6%9C%E5%90%88%E5%B7%A5%E7%A8%8B%E6%9C%89%E9%99%90%E5%85%AC%E5%8F%B8"},"喆昕空間室內裝修設計有限公司":{"name":"喆昕空間室內裝修設計有限公司","id":"95476820","capital":1000000,"representative":"張_瑋","address":"臺南市永康區尚頂里南台街13巷38弄3號1樓","aliases":[],"relationships":{"upstream":[],"downstream":[]},"webUrl":"https://tbdavid2019.github.io/taiwan-company-network/graph?company=%E5%96%86%E6%98%95%E7%A9%BA%E9%96%93%E5%AE%A4%E5%85%A7%E8%A3%9D%E4%BF%AE%E8%A8%AD%E8%A8%88%E6%9C%89%E9%99%90%E5%85%AC%E5%8F%B8"},"喆信設計有限公司":{"name":"喆信設計有限公司","id":"95496754","capital":100000,"representative":"陳_錞","address":"高雄市苓雅區中正二路175號5樓之3","aliases":[],"relationships":{"upstream":[],"downstream":[]},"webUrl":"https://tbdavid2019.github.io/taiwan-company-network/graph?company=%E5%96%86%E4%BF%A1%E8%A8%AD%E8%A8%88%E6%9C%89%E9%99%90%E5%85%AC%E5%8F%B8"},"喆盛有限公司":{"name":"喆盛有限公司","id":"96828817","capital":1000000,"representative":"廖_凱","address":"新北市泰山區福興三街183號5樓","aliases":[],"relationships":{"upstream":[],"downstream":[]},"webUrl":"https://tbdavid2019.github.io/taiwan-company-network/graph?company=%E5%96%86%E7%9B%9B%E6%9C%89%E9%99%90%E5%85%AC%E5%8F%B8"},"喆新展業股份有限公司":{"name":"喆新展業股份有限公司","id":"97508587","capital":4000000,"representative":"高_忠","address":"桃園市桃園區復興路51之2號10樓之1","aliases":[],"relationships":{"upstream":["喆創企業有限公司"],"downstream":[]},"webUrl":"https://tbdavid2019.github.io/taiwan-company-network/graph?company=%E5%96%86%E6%96%B0%E5%B1%95%E6%A5%AD%E8%82%A1%E4%BB%BD%E6%9C%89%E9%99%90%E5%85%AC%E5%8F%B8"},"喆亮國際有限公司":{"name":"喆亮國際有限公司","id":null,"capital":null,"representative":null,"address":null,"aliases":[],"relationships":{"upstream":[],"downstream":["宗遠建築開發股份有限公司"]},"webUrl":"https://tbdavid2019.github.io/taiwan-company-network/graph?company=%E5%96%86%E4%BA%AE%E5%9C%8B%E9%9A%9B%E6%9C%89%E9%99%90%E5%85%AC%E5%8F%B8"}}}