{"shard":"庇","count":8,"data":{"庇蔭創造有限公司":{"name":"庇蔭創造有限公司","id":"62258270","capital":500000,"representative":"林_達","address":"新北市三重區重陽路4段130號12樓","aliases":[],"relationships":{"upstream":[],"downstream":[]},"webUrl":"https://taiwan-company-network.david888.com/graph?company=%E5%BA%87%E8%94%AD%E5%89%B5%E9%80%A0%E6%9C%89%E9%99%90%E5%85%AC%E5%8F%B8"},"庇后有限公司":{"name":"庇后有限公司","id":"83699615","capital":200000,"representative":"湯_華","address":"臺北市信義區永吉路443巷11弄1號2樓","aliases":[],"relationships":{"upstream":[],"downstream":[]},"webUrl":"https://taiwan-company-network.david888.com/graph?company=%E5%BA%87%E5%90%8E%E6%9C%89%E9%99%90%E5%85%AC%E5%8F%B8"},"庇卡任意門健康顧問有限公司":{"name":"庇卡任意門健康顧問有限公司","id":"90324846","capital":5000000,"representative":"尹_風","address":"臺北市中山區中山北路2段99號4樓之1","aliases":[],"relationships":{"upstream":[],"downstream":[]},"webUrl":"https://taiwan-company-network.david888.com/graph?company=%E5%BA%87%E5%8D%A1%E4%BB%BB%E6%84%8F%E9%96%80%E5%81%A5%E5%BA%B7%E9%A1%A7%E5%95%8F%E6%9C%89%E9%99%90%E5%85%AC%E5%8F%B8"},"庇海開發股份有限公司":{"name":"庇海開發股份有限公司","id":"90489396","capital":100000,"representative":"謝_漳","address":"臺南市中西區南美里民生路1段167號3樓","aliases":[],"relationships":{"upstream":[],"downstream":[]},"webUrl":"https://taiwan-company-network.david888.com/graph?company=%E5%BA%87%E6%B5%B7%E9%96%8B%E7%99%BC%E8%82%A1%E4%BB%BD%E6%9C%89%E9%99%90%E5%85%AC%E5%8F%B8"},"庇俄斯科技股份有限公司":{"name":"庇俄斯科技股份有限公司","id":"53695893","capital":20000000,"representative":"賴_源","address":"彰化縣彰化市民生里三民路204號","aliases":[],"relationships":{"upstream":[],"downstream":[]},"webUrl":"https://taiwan-company-network.david888.com/graph?company=%E5%BA%87%E4%BF%84%E6%96%AF%E7%A7%91%E6%8A%80%E8%82%A1%E4%BB%BD%E6%9C%89%E9%99%90%E5%85%AC%E5%8F%B8"},"庇爾司生技股份有限公司":{"name":"庇爾司生技股份有限公司","id":"83270970","capital":1200000,"representative":"許_華","address":"高雄市左營區華欣路98號14樓","aliases":[],"relationships":{"upstream":[],"downstream":[]},"webUrl":"https://taiwan-company-network.david888.com/graph?company=%E5%BA%87%E7%88%BE%E5%8F%B8%E7%94%9F%E6%8A%80%E8%82%A1%E4%BB%BD%E6%9C%89%E9%99%90%E5%85%AC%E5%8F%B8"},"庇嶼創意有限公司":{"name":"庇嶼創意有限公司","id":"90003507","capital":600000,"representative":"陳_名","address":"新北市新莊區瓊泰路215號","aliases":[],"relationships":{"upstream":[],"downstream":[]},"webUrl":"https://taiwan-company-network.david888.com/graph?company=%E5%BA%87%E5%B6%BC%E5%89%B5%E6%84%8F%E6%9C%89%E9%99%90%E5%85%AC%E5%8F%B8"},"庇海一號能源股份有限公司":{"name":"庇海一號能源股份有限公司","id":"94006061","capital":1100000,"representative":"吳_昱","address":"臺南市中西區淺草里金華路3段230號3樓之1","aliases":[],"relationships":{"upstream":[],"downstream":[]},"webUrl":"https://taiwan-company-network.david888.com/graph?company=%E5%BA%87%E6%B5%B7%E4%B8%80%E8%99%9F%E8%83%BD%E6%BA%90%E8%82%A1%E4%BB%BD%E6%9C%89%E9%99%90%E5%85%AC%E5%8F%B8"}}}