{"shard":"淥","count":7,"data":{"淥泰投資有限公司":{"name":"淥泰投資有限公司","id":"42979078","capital":100000,"representative":"黃_惠","address":"雲林縣崙背鄉水尾村下街路54-1號  ","aliases":[],"relationships":{"upstream":[],"downstream":[]},"webUrl":"https://taiwan-company-network.david888.com/graph?company=%E6%B7%A5%E6%B3%B0%E6%8A%95%E8%B3%87%E6%9C%89%E9%99%90%E5%85%AC%E5%8F%B8"},"淥傳宏有限公司":{"name":"淥傳宏有限公司","id":"62222793","capital":100000,"representative":"陳_琪","address":"臺北市中正區重慶南路1段57號10樓之17","aliases":[],"relationships":{"upstream":[],"downstream":[]},"webUrl":"https://taiwan-company-network.david888.com/graph?company=%E6%B7%A5%E5%82%B3%E5%AE%8F%E6%9C%89%E9%99%90%E5%85%AC%E5%8F%B8"},"淥泰能源發展股份有限公司":{"name":"淥泰能源發展股份有限公司","id":"84818603","capital":5000000,"representative":"黃_惠","address":"雲林縣崙背鄉水尾村下街路54之1號1樓","aliases":[],"relationships":{"upstream":[],"downstream":[]},"webUrl":"https://taiwan-company-network.david888.com/graph?company=%E6%B7%A5%E6%B3%B0%E8%83%BD%E6%BA%90%E7%99%BC%E5%B1%95%E8%82%A1%E4%BB%BD%E6%9C%89%E9%99%90%E5%85%AC%E5%8F%B8"},"淥米薾餐飲有限公司":{"name":"淥米薾餐飲有限公司","id":"85009333","capital":6000000,"representative":"張_茂","address":"高雄市前金區光復三街118號","aliases":[],"relationships":{"upstream":[],"downstream":[]},"webUrl":"https://taiwan-company-network.david888.com/graph?company=%E6%B7%A5%E7%B1%B3%E8%96%BE%E9%A4%90%E9%A3%B2%E6%9C%89%E9%99%90%E5%85%AC%E5%8F%B8"},"淥淞有限公司":{"name":"淥淞有限公司","id":"145543","capital":100000,"representative":"李_蓉","address":"臺北市大安區信義路4段1號2樓","aliases":[],"relationships":{"upstream":[],"downstream":[]},"webUrl":"https://taiwan-company-network.david888.com/graph?company=%E6%B7%A5%E6%B7%9E%E6%9C%89%E9%99%90%E5%85%AC%E5%8F%B8"},"淥青企業有限公司":{"name":"淥青企業有限公司","id":"4942067","capital":1000000,"representative":"楊_卿","address":"臺北市松山區信義路3段166巷4號","aliases":[],"relationships":{"upstream":[],"downstream":[]},"webUrl":"https://taiwan-company-network.david888.com/graph?company=%E6%B7%A5%E9%9D%92%E4%BC%81%E6%A5%AD%E6%9C%89%E9%99%90%E5%85%AC%E5%8F%B8"},"淥清企業有限公司":{"name":"淥清企業有限公司","id":"23546926","capital":5000000,"representative":"梁_龍","address":"新北市板橋區僑中二街12巷10號(1樓)","aliases":[],"relationships":{"upstream":[],"downstream":[]},"webUrl":"https://taiwan-company-network.david888.com/graph?company=%E6%B7%A5%E6%B8%85%E4%BC%81%E6%A5%AD%E6%9C%89%E9%99%90%E5%85%AC%E5%8F%B8"}}}