{"shard":"瀀","count":3,"data":{"瀀霓科技股份有限公司":{"name":"瀀霓科技股份有限公司","id":"83144756","capital":0,"representative":"楊_仁","address":"臺中市大里區西榮里西榮路80巷3號1樓","aliases":[],"relationships":{"upstream":[],"downstream":[]},"webUrl":"https://taiwan-company-network.david888.com/graph?company=%E7%80%80%E9%9C%93%E7%A7%91%E6%8A%80%E8%82%A1%E4%BB%BD%E6%9C%89%E9%99%90%E5%85%AC%E5%8F%B8"},"瀀世綠能有限公司":{"name":"瀀世綠能有限公司","id":"24968992","capital":5000000,"representative":"謝_芸","address":"臺中市西區民龍里西屯路一段230之8號  ","aliases":[],"relationships":{"upstream":[],"downstream":[]},"webUrl":"https://taiwan-company-network.david888.com/graph?company=%E7%80%80%E4%B8%96%E7%B6%A0%E8%83%BD%E6%9C%89%E9%99%90%E5%85%AC%E5%8F%B8"},"瀀尼課國際有限公司":{"name":"瀀尼課國際有限公司","id":"25154311","capital":200000,"representative":"呂_彥","address":"高雄市苓雅區中正一路１２０號６樓之８","aliases":[],"relationships":{"upstream":[],"downstream":[]},"webUrl":"https://taiwan-company-network.david888.com/graph?company=%E7%80%80%E5%B0%BC%E8%AA%B2%E5%9C%8B%E9%9A%9B%E6%9C%89%E9%99%90%E5%85%AC%E5%8F%B8"}}}