{"shard":"蜷","count":2,"data":{"蜷尾家胖有限公司":{"name":"蜷尾家胖有限公司","id":"89175811","capital":7000000,"representative":"李_豫","address":"臺南市中西區南美里新美街5號1樓","aliases":[],"relationships":{"upstream":[],"downstream":[]},"webUrl":"https://tbdavid2019.github.io/taiwan-company-network/graph?company=%E8%9C%B7%E5%B0%BE%E5%AE%B6%E8%83%96%E6%9C%89%E9%99%90%E5%85%AC%E5%8F%B8"},"蜷尾家投資股份有限公司":{"name":"蜷尾家投資股份有限公司","id":"93748039","capital":5000000,"representative":"李_豫","address":"臺南市安平區金城里安北路720號1樓","aliases":[],"relationships":{"upstream":[],"downstream":["台灣麥姝生活股份有限公司"]},"webUrl":"https://tbdavid2019.github.io/taiwan-company-network/graph?company=%E8%9C%B7%E5%B0%BE%E5%AE%B6%E6%8A%95%E8%B3%87%E8%82%A1%E4%BB%BD%E6%9C%89%E9%99%90%E5%85%AC%E5%8F%B8"}}}